Workbook

Sheet まとめ
B1: ■全体 | G1: ■全体 FY25 | H1: 10/23時点
C2: 確度 | D2: 下期 | E2: Plan1.2 | H2: 確度 | I2: 積上げ | J2: Plan1.3 | K2: Plan1.2 当初
C3: A | D3: =D31+D41+D51 -> 2.762004e+08 | E3: =E31+E41+E51 -> 0 | H3: A | I3: =J31+J41+J51 -> 4.1491302e+08 | J3: =フォロー状況!FP21 -> 0 | K3: 231707997
C4: B | D4: =D32+D42+D52 -> 6490000 | E4: =E32+E42+E52 -> 0 | H4: B | I4: =J32+J42+J52 -> 6490000 | J4: =フォロー状況!FP22 -> 0 | K4: 10000000
C5: C | D5: =D33+D43+D53 -> 9960000 | H5: C | I5: =J33+J43+J53 -> 9960000 | J5: =フォロー状況!FP23 -> 0 | K5: 154970575
B6: Plan1.3テーマ | C6: D | D6: =D34+D44+D54 -> 2700000 | E6: =E33+E43 -> 0 | H6: D | I6: =J34+J44+J54 -> 2700000 | J6: =フォロー状況!FP24 -> 0 | K6: 23308280
B7: 約5000万円獲る！ | C7: O | D7: =D35+D45+D55 -> 0 | E7: =E34+E44+E54 -> 0 | H7: O | I7: =J35+J45+J55 -> 0 | J7: =フォロー状況!FP25 -> 0 | K7: 41500000
C8: 合計 | D8: =SUM(D3:D7) -> 2.953504e+08 | E8: =E36+E46+E56 -> 327233375 | H8: 案件合計 | I8: =SUM(I3:I7) -> 4.3406302e+08 | K8: 461486852
H9: Influence | I9: 35585397 | J9: =J8/K8 -> 0
H11: 売上合計 | I11: =I8+I9 -> 4.6964841e+08
G15: ■対チームKPI：4.5億
H16: 確度 | J16: Plan1.3
H17: A | J17: =J3 -> 0
H18: B | J18: =J4 -> 0 | L18: KPI：4.5億 | M18: FY24：2億500万
H19: C | J19: =J5 -> 0 | K19: =ROUND((SUM(J17:J19)+I9)/100000000,2) -> 0.36 | L19: ="Influence加えた積み上げ"&K19&"億円" -> Influence加えた積み上げ0.36億円
H20: D | J20: =J6 -> 0 | K20: =45000-(K19*10000) -> 41400 | L20: ="KPI達成まであと"&K20&"万円" -> KPI達成まであと41400万円
H21: O | J21: =J7 -> 0
H22: 合計 | J22: =J8 -> 0
B29: ■業務IT | C29: 竹中上振れ、BIM：JSOL新規により想定拡大、Alikiは想定程のびず | G29: FY25上期 | H29: ■業務IT | I29: 竹中上振れ、BIM：JSOL新規により想定拡大、Alikiは想定程のびず | M29: FY25上期
B30: =D36/E36 -> 1.7235195 | C30: 確度 | D30: 下期 | E30: Plan1.2 | I30: 確度 | J30: 通期
B31: =D36-E36 -> 40559326 | C31: A | D31: =フォロー状況!FA6 -> 96617701 | I31: A | J31: =D31+フォロー状況!O26 -> 1.4279873e+08
C32: B | D32: =フォロー状況!FA7 -> 0 | I32: B | J32: =D32 -> 0
C33: C | D33: =フォロー状況!FA8 -> 0 | I33: C | J33: =D33 -> 0
C34: D | D34: =フォロー状況!FA9 -> 0 | I34: D | J34: =D34 -> 0
C35: O | D35: =フォロー状況!FA10 -> 0 | I35: O | J35: =D35 -> 0
C36: 合計 | D36: =フォロー状況!FA11 -> 96617701 | E36: 56058375 | G36: =フォロー状況!O26 -> 46181032 | I36: 合計 | J36: =SUM(J31:J35) -> 1.4279873e+08 | M36: =フォロー状況!U26 -> 0
B39: ■業務改善 | C39: 大末＋青木が想定通り1.2億、TCG、東興、鍜治田など可能性があるので、最後の追い込みに期待
B40: =D46/E46 -> 0.88447232 | C40: 確度 | D40: 下期 | E40: Plan1.2 | I40: 確度 | J40: 通期
B41: =D46-E46 -> -17617971 | C41: A | D41: =フォロー状況!FA30 -> 1.2773203e+08 | I41: A | J41: =D41+フォロー状況!O52 -> 1.8849185e+08
C42: B | D42: =フォロー状況!FA31 -> 6490000 | I42: B | J42: =D42 -> 6490000
C43: C | D43: =フォロー状況!FA32 -> 660000 | I43: C | J43: =D43 -> 660000
B44: Plan1.3テーマ | C44: D | D44: =フォロー状況!FA33 -> 0 | I44: D | J44: =D44 -> 0
C45: O | D45: =フォロー状況!FA34 -> 0 | I45: O | J45: =D45 -> 0
C46: 合計 | D46: =フォロー状況!FA35 -> 1.3488203e+08 | E46: 152500000 | G46: =フォロー状況!O52 -> 60759818 | I46: 合計 | J46: =SUM(J41:J45) -> 1.9564185e+08
B49: ■製造IT | C49: 見込んでいたRPAが軒並みロスト、AI関連で追い込みをかけるも、見込Maxで予算比：58%。提案中1200万円を確実に獲得しつつ、さらなる上積みを目指す。
B50: 0.57915965 | C50: 確度 | D50: 下期 | E50: Plan1.2 | I50: 確度 | J50: 通期
B51: -49943229 | C51: A | D51: =フォロー状況!FA56 -> 51850673 | I51: A | J51: =D51+G56 -> 83622437
C52: B | D52: =フォロー状況!FA57 -> 0 | I52: B | J52: =D52 -> 0
C53: C | D53: =フォロー状況!FA58 -> 9300000 | I53: C | J53: =D53 -> 9300000
B54: Plan1.3テーマ | C54: D | D54: =フォロー状況!FA59 -> 2700000 | I54: D | J54: =D54 -> 2700000
C55: O | D55: =フォロー状況!FA60 -> 0 | I55: O | J55: =D55 -> 0
C56: 合計 | D56: =フォロー状況!FA61 -> 63850673 | E56: 118675000 | G56: =フォロー状況!O77 -> 31771765 | I56: 合計 | J56: =SUM(J51:J55) -> 95622437

Sheet フォロー状況
A1: サブチーム | B1: クライアント名 | C1: PJ名 | E1: コメント | F1: メンバ | G1: 確度 | H1: 粗利率 | I1: 1月 | J1: 2月 | K1: 3月 | L1: 4月 | M1: 5月 | N1: 6月 | O1: 上期実績 | P1: 7月実績 | Q1: 8月見込 | R1: 9月見込 | AW1: 10月見込 | DG1: 11月見込 | EM1: 12月見込 | EN1: 11/4時点 | EO1: 通期 | EP1: Plan1.3 | EQ1: Plan1.3比 | ES1: Plan1.0 | ET1: Plan1.0比 | EV1: チーム別 | FL1: ■Opp Stage定義
P2: 37630035 | Q2: 48249760 | R2: 1 | S2: 2 | T2: 3 | U2: 4 | V2: 5 | W2: 6 | X2: 7 | Y2: 8 | Z2: 9 | AA2: 10 | AB2: 11 | AC2: 12 | AD2: 13 | AE2: 14 | AF2: 15 | AG2: 16 | AH2: 17 | AI2: 18 | AJ2: 19 | AK2: 20 | AL2: 21 | AM2: 22 | AN2: 23 | AO2: 24 | AP2: 25 | AQ2: 26 | AR2: 27 | AS2: 28 | AT2: 29 | AU2: 30 | AV2: 55159910 | AW2: 1 | AX2: 2 | AY2: 3 | AZ2: 4 | BA2: 5 | BB2: 6 | BC2: 7 | BD2: 8 | BE2: 9 | BF2: 10 | BG2: 11 | BH2: 12 | BI2: 13 | BJ2: 14 | BK2: 15 | BL2: 16 | BM2: 17 | BN2: 18 | BO2: 19 | BP2: 20 | BQ2: 21 | BR2: 22 | BS2: 23 | BT2: 24 | BU2: 25 | BV2: 26 | BW2: 27 | BX2: 28 | BY2: 29 | BZ2: 30 | CA2: 31 | CB2: 67657800 | CC2: 1 | CD2: 2 | CE2: 3 | CF2: 4 | CG2: 5 | CH2: 6 | CI2: 7 | CJ2: 8 | CK2: 9 | CL2: 10 | CM2: 11 | CN2: 12 | CO2: 13 | CP2: 14 | CQ2: 15 | CR2: 16 | CS2: 17 | CT2: 18 | CU2: 19 | CV2: 20 | CW2: 21 | CX2: 22 | CY2: 23 | CZ2: 24 | DA2: 25 | DB2: 26 | DC2: 27 | DD2: 28 | DE2: 29 | DF2: 30 | DG2: 60518100 | DH2: 1 | DI2: 2 | DJ2: 3 | DK2: 4 | DL2: 5 | DM2: 6 | DN2: 7 | DO2: 8 | DP2: 9 | DQ2: 10 | DR2: 11 | DS2: 12 | DT2: 13 | DU2: 14 | DV2: 15 | DW2: 16 | DX2: 17 | DY2: 18 | DZ2: 19 | EA2: 20 | EB2: 21 | EC2: 22 | ED2: 23 | EE2: 24 | EF2: 25 | EG2: 26 | EH2: 27 | EI2: 28 | EJ2: 29 | EK2: 30 | EL2: 31 | EM2: 58018250 | EN2: Revenue合計 | EO2: =FH80 -> 4.6851356e+08 | EP2: 4.7804958e+08 | EQ2: =EO2/EP2 -> 0.98005224 | ES2: 473819503 | ET2: =EO2/ES2 -> 0.98880176 | EY2: 下期 | FE2: FY25 通期 | FM2: 区分 | FN2: 受注確率 | FO2: 入れる内容例
EN3: Influence | EO3: =FH78 -> 34450540 | EP3: =FI78 -> 11213805 | EQ3: =EO3/EP3 -> 3.0721545 | ES3: チームKPI | ET3: KPI比
B4: FY25NewLogo | O4: =SUM(O24:O84) -> 1.3871261e+08 | P4: 30620471 | Q4: =SUM(Q5:Q78) -> 44471500 | R4: 月 | S4: 火 | T4: 水 | U4: 木 | V4: 金 | W4: 土 | X4: 日 | Y4: 月 | Z4: 火 | AA4: 水 | AB4: 木 | AC4: 金 | AD4: 土 | AE4: 日 | AF4: 月 | AG4: 火 | AH4: 水 | AI4: 木 | AJ4: 金 | AK4: 土 | AL4: 日 | AM4: 月 | AN4: 火 | AO4: 水 | AP4: 木 | AQ4: 金 | AR4: 土 | AS4: 日 | AT4: 月 | AU4: 火 | AV4: =SUM(AV5:AV78) -> 56143702 | AW4: 水 | AX4: 木 | AY4: 金 | AZ4: 土 | BA4: 日 | BB4: 月 | BC4: 火 | BD4: 水 | BE4: 木 | BF4: 金 | BG4: 土 | BH4: 日 | BI4: 月 | BJ4: 火 | BK4: 水 | BL4: 木 | BM4: 金 | BN4: 土 | BO4: 日 | BP4: 月 | BQ4: 火 | BR4: 水 | BS4: 木 | BT4: 金 | BU4: 土 | BV4: 日 | BW4: 月 | BX4: 火 | BY4: 水 | BZ4: 木 | CA4: 金 | CB4: =SUM(CB5:CB78) -> 51660000 | CC4: 月 | CD4: 火 | CE4: 水 | CF4: 木 | CG4: 金 | CH4: 土 | CI4: 日 | CJ4: 月 | CK4: 火 | CL4: 水 | CM4: 木 | CN4: 金 | CO4: 土 | CP4: 日 | CQ4: 月 | CR4: 火 | CS4: 水 | CT4: 木 | CU4: 金 | CV4: 土 | CW4: 日 | CX4: 月 | CY4: 火 | CZ4: 水 | DA4: 木 | DB4: 金 | DC4: 土 | DD4: 日 | DE4: 月 | DF4: 火 | DG4: =SUM(DG5:DG78) -> 55145000 | DH4: 月 | DI4: 火 | DJ4: 水 | DK4: 木 | DL4: 金 | DM4: 土 | DN4: 日 | DO4: 月 | DP4: 火 | DQ4: 水 | DR4: 木 | DS4: 金 | DT4: 土 | DU4: 日 | DV4: 月 | DW4: 火 | DX4: 水 | DY4: 木 | DZ4: 金 | EA4: 土 | EB4: 日 | EC4: 月 | ED4: 火 | EE4: 水 | EF4: 木 | EG4: 金 | EH4: 土 | EI4: 日 | EJ4: 月 | EK4: 火 | EM4: =SUM(EM5:EM78) -> 57960000 | EN4: 下期積上 | EO4: =SUM(EO5:EO91) -> 3.019704e+08 | EP4: 3.2395067e+08 | EQ4: =EO4/EP4 -> 0.93214933 | ES4: 400000000 | ET4: =EO2/ES4 -> 1.1712839 | EV4: 業務ITT | EW4: Plan1.3 | EY4: Plan1.3比 | EZ4: ■竹中＋BIMで、計画通り推移、竹中上振れ | FE4: 業務IT | FH4: Plan1.3比はInfluence抜き | FM4: O | FN4: 20%以下 | FO4: 白地のもの。オポチュニティーを認識したレベル。
A5: 業務ITT | B5: JSOL Corporation | C5: BIM汎用コンポーネント開発支援 | D5: 継続 | E5: 稼働中 | F5: 中村、天野、田村 | G5: A | H5: 0.57 | P5: 1791049 | Q5: 1980000 | AV5: 1700000 | CB5: 1700000 | DG5: 0 | EM5: 0 | EO5: =P5+Q5+AV5+CB5+DG5+EM5 -> 7171049 | EP5: 7640000 | EQ5: =EO5-EP5 -> -468950.96 | EV5: =SUM(EO5:EO27) -> 96617701 | EW5: =SUM(EP5:EP27) -> 97520000 | EY5: =EV5/EW5 -> 0.99074755 | EZ5: 確度 | FA5: 下期 | FB5: Plan | FE5: Plan1.3比 | FF5: =FH11/FI11 -> 0.96679622 | FG5: 確度 | FH5: 下期 | FI5: Plan1.3 | FJ5: 100%KPI | FM5: D | FN5: 0.5 | FO5: 提案実施済み、もしくは提案実施までは決まっているが受注可否が未定。
A6: 業務ITT | B6: NISHIMATSU CONSTRUCTION CO.,LTD. | C6: BIMモデリング支援 | D6: 継続 | E6: 稼働中（11,12月も継続予定） | F6: 中村 | G6: A | H6: 0.57 | P6: 750000 | Q6: 750000 | AV6: 750000 | CB6: 750000 | DG6: 750000 | EM6: 750000 | EO6: =P6+Q6+AV6+CB6+DG6+EM6 -> 4500000 | EP6: 4500000 | EQ6: =EO6-EP6 -> 0 | EW6: =EV5-EW5 -> -902298.58 | EZ6: A | FA6: =SUMIF($G$5:$G$27,"A",$EO$5:$EO$27) -> 96617701 | FE6: KPI比 | FF6: =FH15/FJ15 -> 1.6392022 | FG6: A | FH6: =SUMIF($G$5:$G$27,"A",$EO$5:$EO$27)+O26 -> 1.4279873e+08 | FM6: C | FN6: 0.8 | FO6: A or Bの案件テーマの継続だが、まだ契約を実施していない。ただほぼ受注は問題ない案件。
A7: 業務ITT | B7: SHIMZ | C7: FM事業支援 | D7: 新規 | E7: 稼働中 | F7: 八巻、趙 | G7: A | H7: 0.46 | P7: 500000 | Q7: 500000 | AV7: 500000 | CB7: 500000 | DG7: 500000 | EM7: 500000 | EO7: =P7+Q7+AV7+CB7+DG7+EM7 -> 3000000 | EP7: 3000000 | EQ7: =EO7-EP7 -> 0 | EZ7: B | FA7: =SUMIF($G$5:$G$27,"B",$EO$5:$EO$27) -> 0 | FG7: B | FH7: =SUMIF($G$5:$G$27,"B",$EO$5:$EO$27) -> 0 | FM7: B | FN7: 0.99 | FO7: 受注したが契約が未締結。
A8: 業務ITT | B8: Takenaka Corporation | C8: BIM基盤構築（3-7月）※コンサル | D8: 継続 | E8: 稼働中 | F8: 八巻、田口、益田、趙、加賀谷 | G8: A | H8: 0.25 | P8: 2206652.4 | Q8: 0 | AV8: 0 | CB8: 0 | DG8: 0 | EM8: 0 | EO8: =P8+Q8+AV8+CB8+DG8+EM8 -> 2206652.4 | EP8: 2360000 | EQ8: =EO8-EP8 -> -153347.62 | EZ8: C | FA8: =SUMIF($G$5:$G$27,"C",$EO$5:$EO$27) -> 0 | FG8: C | FH8: =SUMIF($G$5:$G$27,"C",$EO$5:$EO$27) -> 0 | FM8: A | FN8: 1 | FO8: 受注確定し、契約も実施。
A9: 業務ITT | B9: Takenaka Corporation | C9: BIM基盤構築（8-12月）※コンサル | D9: 継続 | E9: 稼働中 | F9: 八巻、田口、益田、趙、BP | G9: A | H9: 0.25 | P9: 0 | Q9: 8640000 | AV9: 8280000 | CB9: 8480000 | DG9: 8480000 | EM9: 8480000 | EO9: =P9+Q9+AV9+CB9+DG9+EM9 -> 42360000 | EP9: 42360000 | EQ9: =EO9-EP9 -> 0 | ES9: ※梅プラン見積→松プラン増額 | EZ9: D | FA9: =SUMIF($G$5:$G$27,"D",$EO$5:$EO$27) -> 0 | FG9: D | FH9: =SUMIF($G$5:$G$27,"D",$EO$5:$EO$27) -> 0
A10: 業務ITT | B10: Takenaka Corporation | C10: 大阪本店 Akila導入検証 | D10: 新規 | E10: 提案見積提出済み（動きなし） | F10: 八巻、趙 | G10: ー | P10: 0 | Q10: 0 | AV10: 0 | CB10: 0 | DG10: 0 | EM10: 0 | EO10: =P10+Q10+AV10+CB10+DG10+EM10 -> 0 | EP10: 0 | EQ10: =EO10-EP10 -> 0 | ES10: 動きが無いため一旦保留 | EZ10: O | FA10: =SUMIF($G$5:$G$27,"o",$EO$5:$EO$27) -> 0 | FG10: O | FH10: =SUMIF($G$5:$G$27,"o",$EO$5:$EO$27) -> 0
A11: 業務ITT | B11: Takenaka Corporation | C11: 中央監視システム開発支援 | D11: 新規 | E11: 提案見積提出済み（動きなし） | F11: 八巻、田口 | G11: ー | P11: 0 | Q11: 0 | AV11: 0 | CB11: 0 | DG11: 0 | EM11: 0 | EO11: =P11+Q11+AV11+CB11+DG11+EM11 -> 0 | EP11: 0 | EQ11: =EO11-EP11 -> 0 | ES11: 動きが無いため一旦保留 | EZ11: 合計 | FA11: =SUM(FA6:FA10) -> 96617701 | FB11: =EW5 -> 97520000 | FG11: 積上げ | FH11: =SUM(FH6:FH10) -> 1.4279873e+08 | FI11: 147703032
A12: 業務ITT | B12: New Customer（大林組） | C12: デジタルツイン（Akila PoCプラン） | D12: 新規 | E12: 12月受注、契約手続き中。（稼働は1月～3月） | F12: 八巻、天野 | G12: B | P12: 0 | Q12: 0 | CB12: 0 | DG12: 0 | EM12: 0 | EO12: =P12+Q12+AV12+CB12+DG12+EM12 -> 0 | EP12: 280000 | EQ12: =EO12-EP12 -> -280000
A13: 業務ITT | B13: DAISUE CONSTRUCTION CO.,LTD. | C13: BIM動画作成（下期） | D13: 継続 | E13: 12月建設DX展に合わせて実施 | F13: 中村 | G13: A | P13: 0 | Q13: 0 | EM13: 175000 | EO13: =P13+Q13+AV13+CB13+DG13+EM13 -> 175000 | EP13: 175000 | EQ13: =EO13-EP13 -> 0 | FG13: Influence | FH13: =チーム別PreSales!E4 -> 30956700
A14: 業務ITT | B14: JSOL Corporation | C14: 建設DXコンサル支援（ナカノフドー建設） | D14: 新規 | E14: 稼働中（～2026年3月） | F14: 中村、天野 | G14: A | H14: 0.49 | P14: 1960000 | Q14: 1960000 | AV14: 1960000 | CB14: 1960000 | DG14: 1960000 | EM14: 1960000 | EO14: =P14+Q14+AV14+CB14+DG14+EM14 -> 11760000 | EP14: 11760000 | EQ14: =EO14-EP14 -> 0
A15: 業務ITT | B15: DAISUE CONSTRUCTION CO.,LTD. | C15: BIM品質チェックリスト作成協力業務 | D15: 新規 | E15: 完了 | F15: 中村 | G15: A | P15: 150000 | Q15: 0 | AV15: 0 | CB15: 0 | DG15: 0 | EM15: 0 | EO15: =P15+Q15+AV15+CB15+DG15+EM15 -> 150000 | EP15: 150000 | EQ15: =EO15-EP15 -> 0 | FG15: 見込合計 | FH15: =FH11+FH13 -> 1.7375543e+08 | FJ15: 106000000
A16: 業務ITT | B16: New Customer（JR東日本建築設計） | C16: デジタルツイン（Akila PoCプラン） | D16: 新規 | E16: 7/1提案、動きなし。 | F16: 八巻 | G16: ー | P16: 0 | Q16: 0 | R16: 300000 | S16: 300000 | T16: 300000 | U16: 300000 | V16: 300000 | W16: 300000 | X16: 300000 | Y16: 300000 | Z16: 300000 | AA16: 300000 | AB16: 300000 | AC16: 300000 | AD16: 300000 | AE16: 300000 | AF16: 300000 | AG16: 300000 | AH16: 300000 | AI16: 300000 | AJ16: 300000 | AK16: 300000 | AL16: 300000 | AM16: 300000 | AN16: 300000 | AO16: 300000 | AP16: 300000 | AQ16: 300000 | AR16: 300000 | AS16: 300000 | AT16: 300000 | AU16: 300000 | EO16: =P16+Q16+AV16+CB16+DG16+EM16 -> 0 | EP16: 0 | EQ16: =EO16-EP16 -> 0
A17: 業務ITT | B17: New Customer（清水建設） | C17: デジタルツイン（Akila PoCプラン） | D17: 新規 | E17: 8/29見積提出、動きなし。 | F17: 八巻 | G17: ー | P17: 0 | Q17: 0 | R17: 300000 | S17: 300000 | T17: 300000 | U17: 300000 | V17: 300000 | W17: 300000 | X17: 300000 | Y17: 300000 | Z17: 300000 | AA17: 300000 | AB17: 300000 | AC17: 300000 | AD17: 300000 | AE17: 300000 | AF17: 300000 | AG17: 300000 | AH17: 300000 | AI17: 300000 | AJ17: 300000 | AK17: 300000 | AL17: 300000 | AM17: 300000 | AN17: 300000 | AO17: 300000 | AP17: 300000 | AQ17: 300000 | AR17: 300000 | AS17: 300000 | AT17: 300000 | AU17: 300000 | EO17: =P17+Q17+AV17+CB17+DG17+EM17 -> 0 | EP17: 0 | EQ17: =EO17-EP17 -> 0
A18: 業務ITT | B18: New Customer（長谷工） | C18: デジタルツイン（Akila PoCプラン） | D18: 新規 | E18: 6/26会社紹介 | F18: 八巻 | G18: ー | P18: 0 | Q18: 0 | R18: 300000 | S18: 300000 | T18: 300000 | U18: 300000 | V18: 300000 | W18: 300000 | X18: 300000 | Y18: 300000 | Z18: 300000 | AA18: 300000 | AB18: 300000 | AC18: 300000 | AD18: 300000 | AE18: 300000 | AF18: 300000 | AG18: 300000 | AH18: 300000 | AI18: 300000 | AJ18: 300000 | AK18: 300000 | AL18: 300000 | AM18: 300000 | AN18: 300000 | AO18: 300000 | AP18: 300000 | AQ18: 300000 | AR18: 300000 | AS18: 300000 | AT18: 300000 | AU18: 300000 | EO18: =P18+Q18+AV18+CB18+DG18+EM18 -> 0 | EP18: 0 | EQ18: =EO18-EP18 -> 0
A19: 業務ITT | B19: New Customer（住友商事） | C19: デジタルツイン（Akila PoCプラン） | D19: 新規 | E19: BCOアポ取り中 | F19: 八巻 | G19: ー | P19: 0 | Q19: 0 | R19: 300000 | S19: 300000 | T19: 300000 | U19: 300000 | V19: 300000 | W19: 300000 | X19: 300000 | Y19: 300000 | Z19: 300000 | AA19: 300000 | AB19: 300000 | AC19: 300000 | AD19: 300000 | AE19: 300000 | AF19: 300000 | AG19: 300000 | AH19: 300000 | AI19: 300000 | AJ19: 300000 | AK19: 300000 | AL19: 300000 | AM19: 300000 | AN19: 300000 | AO19: 300000 | AP19: 300000 | AQ19: 300000 | AR19: 300000 | AS19: 300000 | AT19: 300000 | AU19: 300000 | EO19: =P19+Q19+AV19+CB19+DG19+EM19 -> 0 | EP19: 0 | EQ19: =EO19-EP19 -> 0
A20: 業務ITT | B20: New Customer（ファーストリテイリング） | C20: デジタルツイン（Akila PoCプラン） | D20: 新規 | E20: BCOアポ取り中 | F20: 八巻 | G20: ー | P20: 0 | Q20: 0 | R20: 300000 | S20: 300000 | T20: 300000 | U20: 300000 | V20: 300000 | W20: 300000 | X20: 300000 | Y20: 300000 | Z20: 300000 | AA20: 300000 | AB20: 300000 | AC20: 300000 | AD20: 300000 | AE20: 300000 | AF20: 300000 | AG20: 300000 | AH20: 300000 | AI20: 300000 | AJ20: 300000 | AK20: 300000 | AL20: 300000 | AM20: 300000 | AN20: 300000 | AO20: 300000 | AP20: 300000 | AQ20: 300000 | AR20: 300000 | AS20: 300000 | AT20: 300000 | AU20: 300000 | EO20: =P20+Q20+AV20+CB20+DG20+EM20 -> 0 | EP20: 0 | EQ20: =EO20-EP20 -> 0
A21: 業務ITT | B21: New Customer（ニトリ） | C21: デジタルツイン（Akila PoCプラン） | D21: 新規 | E21: BCOアポ取り中 | F21: 八巻 | G21: ー | P21: 0 | Q21: 0 | R21: 300000 | S21: 300000 | T21: 300000 | U21: 300000 | V21: 300000 | W21: 300000 | X21: 300000 | Y21: 300000 | Z21: 300000 | AA21: 300000 | AB21: 300000 | AC21: 300000 | AD21: 300000 | AE21: 300000 | AF21: 300000 | AG21: 300000 | AH21: 300000 | AI21: 300000 | AJ21: 300000 | AK21: 300000 | AL21: 300000 | AM21: 300000 | AN21: 300000 | AO21: 300000 | AP21: 300000 | AQ21: 300000 | AR21: 300000 | AS21: 300000 | AT21: 300000 | AU21: 300000 | EO21: =P21+Q21+AV21+CB21+DG21+EM21 -> 0 | EP21: 0 | EQ21: =EO21-EP21 -> 0
A22: 業務ITT | B22: New Customer（資生堂） | C22: デジタルツイン（Akila PoCプラン） | D22: 新規 | E22: BCOアポ取り中 | F22: 八巻 | G22: ー | P22: 0 | Q22: 0 | R22: 300000 | S22: 300000 | T22: 300000 | U22: 300000 | V22: 300000 | W22: 300000 | X22: 300000 | Y22: 300000 | Z22: 300000 | AA22: 300000 | AB22: 300000 | AC22: 300000 | AD22: 300000 | AE22: 300000 | AF22: 300000 | AG22: 300000 | AH22: 300000 | AI22: 300000 | AJ22: 300000 | AK22: 300000 | AL22: 300000 | AM22: 300000 | AN22: 300000 | AO22: 300000 | AP22: 300000 | AQ22: 300000 | AR22: 300000 | AS22: 300000 | AT22: 300000 | AU22: 300000 | EO22: =P22+Q22+AV22+CB22+DG22+EM22 -> 0 | EP22: 0 | EQ22: =EO22-EP22 -> 0
A23: 業務ITT | B23: Takenaka Corporation | C23: BIM基盤構築（開発） | D23: 継続 | E23: 稼働中（～2026年12月） | F23: 田口 | G23: A | H23: 0.25 | P23: 0 | Q23: 0 | AV23: 2000000 | CB23: 2000000 | DG23: 2000000 | EM23: 2000000 | EO23: =P23+Q23+AV23+CB23+DG23+EM23 -> 8000000 | EP23: 8000000 | EQ23: =EO23-EP23 -> 0
A24: 業務ITT | B24: JSOL Corporation | C24: 建設DXコンサル支援（ピーエスコンストラクション） | D24: 新規 | E24: 稼働中（～2026年3月） | F24: 八巻、田村 | G24: A | H24: 0.49 | P24: 0 | Q24: 1200000 | AV24: 2280000 | CB24: 1880000 | DG24: 1880000 | EM24: 1880000 | EO24: =P24+Q24+AV24+CB24+DG24+EM24 -> 9120000 | EP24: 9120000 | EQ24: =EO24-EP24 -> 0
A25: 業務ITT | B25: DAISUE CONSTRUCTION CO.,LTD. | C25: 3Dでの整合性確認の事例紹介の動画作成業務 | D25: 新規 | E25: 完了 | F25: 中村、久保田 | G25: A | AV25: 175000 | EO25: =P25+Q25+AV25+CB25+DG25+EM25 -> 175000 | EP25: 175000 | EQ25: =EO25-EP25 -> 0
A26: 業務ITT | B26: 実績積みあげ | I26: 2500050 | J26: 12150000 | K26: 8457600 | L26: 7093924.5 | M26: 8629289.5 | N26: 7350167.5 | O26: =SUM(I26:N26) -> 46181032
A27: 業務ITT | B27: Takenaka Corporation | C27: DLM基盤構築（開発） | D27: 新規 | E27: 稼働中（～2026年12月） | F27: 千葉 | G27: A | H27: 0.2 | AV27: 2000000 | CB27: 2000000 | DG27: 2000000 | EM27: 2000000 | EO27: =P27+Q27+AV27+CB27+DG27+EM27 -> 8000000 | EP27: 8000000 | EQ27: =EO27-EP27 -> 0 | FE27: FY25 通期
A28: 業務改善T | B28: Asunaro Aoki Construction Co.,Ltd. | C28: AAK_スマートBPO業務・方針整理（1月～9月） | D28: 継続 | E28: 稼働中 | F28: 又地、石川、平塚、京地 | G28: A | H28: 0.54 | P28: 2157153.7 | Q28: 2100000 | AV28: 2100000 | CB28: 0 | DG28: 0 | EM28: 0 | EO28: =P28+Q28+AV28+CB28+DG28+EM28 -> 6357153.7 | EP28: 6300000 | EQ28: =EO28-EP28 -> 57153.718 | EV28: 業務改善T | EW28: Plan1.3 | EY28: Plan1.3比 | FE28: 業務改善 | FH28: Plan1.3比はInfluence抜き
A29: 業務改善T | B29: Asunaro Aoki Construction Co.,Ltd. | C29: AAK_スマートBPO業務・方針整理（10月～12月） | D29: 継続 | E29: 受注確定：契約手続き中 | F29: 又地、石川、平塚、京地 | G29: A | P29: 0 | Q29: 0 | AV29: 0 | CB29: 2100000 | DG29: 2100000 | EM29: 2100000 | EO29: =P29+Q29+AV29+CB29+DG29+EM29 -> 6300000 | EP29: 6300000 | EQ29: =EO29-EP29 -> 0 | EV29: =SUM(EO28:EO53) -> 1.3488203e+08 | EW29: =SUM(EP28:EP53) -> 158680000 | EY29: =EV29/EW29 -> 0.85002539 | EZ29: 確度 | FA29: 下期 | FB29: Plan | FE29: Plan1.3比 | FF29: =FH35/FI35 -> 0.93545958 | FG29: 確度 | FH29: 下期 | FI29: Plan1.3 | FJ29: 100%KPI
A30: 業務改善T | B30: Asunaro Aoki Construction Co.,Ltd. | C30: 業務改善（1月～9月） | D30: 継続 | E30: 稼働中 | F30: 又地、石川、平塚、京地 | G30: A | H30: 0.37 | P30: 4600000 | Q30: 4600000 | AV30: 4600000 | CB30: 0 | DG30: 0 | EM30: 0 | EO30: =P30+Q30+AV30+CB30+DG30+EM30 -> 13800000 | EP30: 13800000 | EQ30: =EO30-EP30 -> 0 | EW30: =EV29-EW29 -> -23797971 | EZ30: A | FA30: =SUMIF($G$28:$G$53,EZ30,$EO$28:$EO$53) -> 1.2773203e+08 | FE30: KPI比 | FF30: =FH39/FJ39 -> 1.2273492 | FG30: A | FH30: =SUMIF($G$28:$G$53,FG30,$EO$28:$EO$53)+O100+O52 -> 1.8849185e+08
A31: 業務改善T | B31: Asunaro Aoki Construction Co.,Ltd. | C31: 業務改善（10月～12月） | D31: 継続 | E31: 受注確定：契約手続き中 | F31: 又地、石川、平塚、京地 | G31: A | P31: 0 | Q31: 0 | AV31: 0 | CB31: 2250000 | DG31: 2250000 | EM31: 1500000 | EO31: =P31+Q31+AV31+CB31+DG31+EM31 -> 6000000 | EP31: 6000000 | EQ31: =EO31-EP31 -> 0 | EZ31: B | FA31: =SUMIF($G$28:$G$53,EZ31,$EO$28:$EO$53) -> 6490000 | FG31: B | FH31: =SUMIF($G$28:$G$53,FG31,$EO$28:$EO$53) -> 6490000
A32: 業務改善T | B32: DAISUE CONSTRUCTION CO.,LTD. | C32: [Renew] DX system AMS phase（1月～9月） | D32: 継続 | E32: 稼働中 | F32: 中村、久保田 | G32: A | P32: 750000 | Q32: 750000 | AV32: 750000 | CB32: 0 | DG32: 0 | EM32: 0 | EO32: =P32+Q32+AV32+CB32+DG32+EM32 -> 2250000 | EP32: 2250000 | EQ32: =EO32-EP32 -> 0 | EZ32: C | FA32: =SUMIF($G$28:$G$53,EZ32,$EO$28:$EO$53) -> 660000 | FG32: C | FH32: =SUMIF($G$28:$G$53,FG32,$EO$28:$EO$53) -> 660000
A33: 業務改善T | B33: DAISUE CONSTRUCTION CO.,LTD. | C33: [Renew] DX system AMS phase（10月～12月） | D33: 継続 | E33: 受注確定：契約手続き中 | F33: 中村、久保田 | G33: A | P33: 0 | Q33: 0 | AV33: 0 | CB33: 750000 | DG33: 750000 | EM33: 750000 | EO33: =P33+Q33+AV33+CB33+DG33+EM33 -> 2250000 | EP33: 2250000 | EQ33: =EO33-EP33 -> 0 | EZ33: D | FA33: =SUMIF($G$28:$G$53,EZ33,$EO$28:$EO$53) -> 0 | FG33: D | FH33: =SUMIF($G$28:$G$53,FG33,$EO$28:$EO$53) -> 0
A34: 業務改善T | B34: DAISUE CONSTRUCTION CO.,LTD. | C34: DXS-2 | D34: 継続 | E34: 先方リソース不足により当初の予定より遅延。開始に向けて請求外支援中 | F34: 加藤、久保田 | G34: - | P34: 0 | Q34: 0 | AV34: 0 | CB34: 0 | DG34: 0 | EM34: 0 | EO34: =P34+Q34+AV34+CB34+DG34+EM34 -> 0 | EP34: 1400000 | EQ34: =EO34-EP34 -> -1400000 | EZ34: O | FA34: =SUMIF($G$28:$G$53,EZ34,$EO$28:$EO$53) -> 0 | FG34: O | FH34: =SUMIF($G$28:$G$53,FG34,$EO$28:$EO$53) -> 0
A35: 業務改善T | B35: DAISUE CONSTRUCTION CO.,LTD. | C35: ラクタス新規開発（DXS２遅延の穴埋め） | D35: 新規 | E35: 10月スタートで提案書最終版提出済み。確定待ち | F35: 加藤、久保田 | G35: A | P35: 0 | Q35: 0 | AV35: 0 | CB35: 600000 | DG35: 600000 | EM35: 0 | EO35: =P35+Q35+AV35+CB35+DG35+EM35 -> 1200000 | EP35: 1600000 | EQ35: =EO35-EP35 -> -400000 | ES35: DXS２の穴埋め | EZ35: 合計 | FA35: =SUM(FA30:FA34) -> 1.3488203e+08 | FB35: =SUM(ES28:ES53) -> 0 | FG35: 積上げ | FH35: =SUM(FH30:FH34) -> 1.9564185e+08 | FI35: 209139818
A36: 業務改善T | B36: DAISUE CONSTRUCTION CO.,LTD. | C36: 基幹システムリプレイス（1月～9月） | D36: 継続 | E36: 稼働中 | F36: 加藤、多ケ谷 | G36: A | H36: 0.37 | P36: 12234876 | Q36: 12320000 | AV36: 12320000 | CB36: 0 | DG36: 0 | EM36: 0 | EO36: =P36+Q36+AV36+CB36+DG36+EM36 -> 36874876 | EP36: 36960000 | EQ36: =EO36-EP36 -> -85124.4
A37: 業務改善T | B37: DAISUE CONSTRUCTION CO.,LTD. | C37: 基幹システムリプレイス（10月～12月） | D37: 継続 | E37: 受注ほぼ確定：当初より150万程度の増額、先方社内で稟申中。確定待ち | F37: 加藤、多ケ谷 | G37: A | P37: 0 | Q37: 0 | AV37: 0 | CB37: 11660000 | DG37: 11660000 | EM37: 10540000 | EO37: =P37+Q37+AV37+CB37+DG37+EM37 -> 33860000 | EP37: 31620000 | EQ37: =EO37-EP37 -> 2240000 | FG37: Influence | FH37: =チーム別PreSales!E5 -> 734028.75
A38: 業務改善T | B38: アプリ展開①：鍜治田工務店（大末横展開） | C38: DXS展開 | D38: 新規 | E38: 7/17に三田来訪。協議継続中。次回は9月。来期予算取り | F38: 加藤 | G38: ー | P38: 0 | Q38: 0 | AV38: 0 | CB38: 0 | DG38: 0 | EM38: 0 | EO38: =P38+Q38+AV38+CB38+DG38+EM38 -> 0 | EP38: 0 | EQ38: =EO38-EP38 -> 0
A39: 業務改善T | B39: アプリ展開②：りんかい日産建設他（大末横展開） | C39: DXS展開 | D39: 新規 | E39: 大末からの横展開が困難、個別アポどり難航。TCG基幹次第で中断する方針 | F39: 加藤 | G39: ー | P39: 0 | Q39: 0 | AV39: 0 | CB39: 0 | DG39: 0 | EM39: 0 | EO39: =P39+Q39+AV39+CB39+DG39+EM39 -> 0 | EP39: 0 | EQ39: =EO39-EP39 -> 0 | FG39: 見込合計 | FH39: =FH35+FH37 -> 1.9637588e+08 | FJ39: 160000000
A40: 業務改善T | B40: アプリ展開③：錢高組他（大末横展開） | C40: DXS展開 | D40: 新規 | E40: 大末からの横展開が困難、個別アポどり難航。TCG基幹次第で中断する方針 | F40: 加藤 | G40: ー | P40: 0 | Q40: 0 | AV40: 0 | CB40: 0 | DG40: 0 | EM40: 0 | EO40: =P40+Q40+AV40+CB40+DG40+EM40 -> 0 | EP40: 0 | EQ40: =EO40-EP40 -> 0
A41: 業務改善T | B41: 髙松コンストラクショングループ | C41: 基幹：業務調査・要件整理・RFPのネタ作成 | D41: 新規 | E41: 提案4回、最有力だが先方意思決定難航。PJTはAA主管、コンサル選定はTCGとのこと。望月社長経由でのプッシュ継続。 | F41: 加藤 | G41: ー | P41: 0 | Q41: 0 | AV41: 0 | CB41: 0 | DG41: 0 | EM41: 0 | EO41: =P41+Q41+AV41+CB41+DG41+EM41 -> 0 | EP41: 36000000 | EQ41: =EO41-EP41 -> -36000000 | ES41: （WIP:1億弱）
A42: 業務改善T | B42: 東興ジオテック | C42: 業務調査、要件整理／ICT施工戦略支援 | D42: 新規 | E42: 業務調査＋ICT施工で受注確定（10/30） | F42: 加藤、境 | G42: A | P42: 0 | Q42: 0 | AV42: 0 | CB42: 0 | DG42: 3180000 | EM42: 6360000 | EO42: =P42+Q42+AV42+CB42+DG42+EM42 -> 9540000 | EP42: 0 | EQ42: =EO42-EP42 -> 9540000 | ES42: 1.5か月に 10/23
A43: 業務改善T | B43: Asunaro Aoki Construction Co.,Ltd. | C43: 水中ブルドーザー市場調査 | D43: 新規 | E43: 望月様紹介により土木事業部の市場調査を受注 | F43: 瀬田、又地、田村 | G43: A | H43: 0.55 | P43: 0 | Q43: 2200000 | AV43: 2200000 | CB43: 0 | DG43: 0 | EM43: 0 | EO43: =P43+Q43+AV43+CB43+DG43+EM43 -> 4400000 | EP43: 4400000 | EQ43: =EO43-EP43 -> 0 | ES43: 市場調査1千万
A44: 業務改善T | B44: Asunaro Aoki Construction Co.,Ltd. | C44: 水中ブルドーザービジネス支援 | D44: 継続 | E44: 市場調査後の、各種資料作成・PMO 11月～1月 3か月 105万円×3 | F44: 又地 | G44: B | P44: 0 | Q44: 0 | AV44: 0 | BM44: ▲総額・期間合意 | CB44: 0 | DG44: 1050000 | EM44: 1050000 | EO44: =P44+Q44+AV44+CB44+DG44+EM44 -> 2100000 | EP44: 1000000 | EQ44: =EO44-EP44 -> 1100000 | ES44: FY26の1月まで（1月で105万円）
A45: 業務改善T | B45: Asunaro Aoki Construction Co.,Ltd. | C45: データセンター市場調査 | D45: 継続 | E45: 市場調査後の、各種資料作成・PMO。10/24頃までには判明？ | F45: 加藤、又地 | G45: - | P45: 0 | Q45: 0 | AV45: 0 | CB45: 0 | CC45: 0 | CD45: 0 | CE45: 0 | CF45: 0 | CG45: 0 | CH45: 0 | CI45: 0 | CJ45: 0 | CK45: 0 | CL45: 0 | CM45: 0 | CN45: 0 | CO45: 0 | CP45: 0 | CQ45: 0 | CR45: 0 | CS45: 0 | CT45: 0 | CU45: 0 | CV45: 0 | CW45: 0 | CX45: 0 | CY45: 0 | CZ45: 0 | DA45: 0 | DB45: 0 | DC45: 0 | DD45: 0 | DE45: 0 | DF45: 0 | DG45: 0 | DH45: 0 | DI45: 0 | DJ45: 0 | DK45: 0 | DL45: 0 | DM45: 0 | DN45: 0 | DO45: 0 | DP45: 0 | DQ45: 0 | DR45: 0 | DS45: 0 | DT45: 0 | DU45: 0 | DV45: 0 | DW45: 0 | DX45: 0 | DY45: 0 | DZ45: 0 | EA45: 0 | EB45: 0 | EC45: 0 | ED45: 0 | EE45: 0 | EF45: 0 | EG45: 0 | EH45: 0 | EI45: 0 | EJ45: 0 | EK45: 0 | EL45: 0 | EM45: 0 | EO45: =P45+Q45+AV45+CB45+DG45+EM45 -> 0 | EP45: 0 | EQ45: =EO45-EP45 -> 0 | ES45: コンペ後、ロスト
A46: 業務改善T | B46: Asunaro Aoki Construction Co.,Ltd. | C46: GX市場調査 | D46: 新規 | E46: 水中ブルドーザー市場調査を評価頂き更に別件の土木の市場調査を受注 | F46: 瀬田、又地、境 | G46: A | P46: 0 | AV46: 2600000 | CB46: 2300000 | DG46: 0 | EM46: 0 | EO46: =P46+Q46+AV46+CB46+DG46+EM46 -> 4900000 | EP46: 4900000 | EQ46: =EO46-EP46 -> 0
A47: 業務改善T | B47: Asunaro Aoki Construction Co.,Ltd. | C47: 経営管理システム構築 | D47: 新規 | E47: 基幹刷新に伴うAA周辺システムの構築→受注確定（10/31) | F47: 加藤、京地 | G47: B | P47: 0 | DG47: 980000 | EM47: 2410000 | EO47: =P47+Q47+AV47+CB47+DG47+EM47 -> 3390000 | EQ47: =EO47-EP47 -> 3390000 | ES47: FY26の1月まで（1月241万円、その後も継続予定）
A48: 業務改善T | B48: 野村不動産 | C48: 財務諸表統合BI | D48: 新規 | E48: 10月11月 ※金額はこれから | F48: 多ケ谷 | G48: B | AN48: 3000000 | AO48: 0 | AP48: 3000000 | AQ48: 3000000 | AR48: 0 | AS48: 0 | AT48: 3000000 | BJ48: ▲提案 | CB48: 0 | EM48: 1000000 | EO48: =P48+Q48+AV48+CB48+DG48+EM48 -> 1000000 | EQ48: =EO48-EP48 -> 1000000
A49: 業務改善T | B49: 野村不動産 | C49: 海外案件管理システム | D49: 新規 | E49: 12月に入るかもしれないが基本は1月以降、コンペとのこと | F49: 多ケ谷 | G49: - | Q49: 0 | AV49: 0 | BS49: ▲案件説明 | BW49: 11月に提案・コンペの | CB49: 0 | DG49: 0 | EM49: 0 | EO49: =P49+Q49+AV49+CB49+DG49+EM49 -> 0 | EP49: 3000000 | EQ49: =EO49-EP49 -> -3000000
A50: 業務改善T | B50: LIXIL | C50: AIOCR | D50: 新規 | E50: 多ケ谷さん提案継続。11月から0.1程度で支援開始、結果待ち→失注 | F50: 多ケ谷 | G50: ー | CB50: 0 | DG50: 0 | EM50: 0 | EO50: =P50+Q50+AV50+CB50+DG50+EM50 -> 0 | EP50: 900000 | EQ50: =EO50-EP50 -> -900000
A51: 業務改善T | B51: 三菱食品 | C51: BX-BXのABR（河合さんより） | D51: 新規 | E51: 多ケ谷さんが11月～12月で0.1 | F51: 多ケ谷 | G51: C | CB51: 0 | DG51: 330000 | EM51: 330000 | EO51: =P51+Q51+AV51+CB51+DG51+EM51 -> 660000 | EQ51: =EO51-EP51 -> 660000
A52: 業務改善T | B52: 実績積みあげ | I52: 4598949 | J52: 16628199 | K52: 9867900.5 | L52: 5676864.8 | M52: 5751326.3 | N52: 18236578 | O52: =SUM(I52:N52) -> 60759818
A53: 業務改善T | B53: LIXIL | C53: 深谷工場運用保守 | D53: 新規 | E53: FSJにて対応している案件が炎上、管理者として多ケ谷さんが少ない稼働で入る。8月開始 | F53: 多ケ谷 | G53: ー | Q53: 0 | AV53: 0 | EO53: =P53+Q53+AV53+CB53+DG53+EM53 -> 0 | EP53: 0 | EQ53: =EO53-EP53 -> 0 | EY53: 製造IT | FE53: FY25 通期
A54: 製造T | B54: Daifuku Co., Ltd. | C54: 3D CADチェックツール開発(第二弾) | D54: 継続 | E54: 9月分対応完了 | F54: 川口 | G54: A | P54: 0 | Q54: 46500 | AV54: 46500 | CB54: 0 | DG54: 0 | EM54: 0 | EO54: =P54+Q54+AV54+CB54+DG54+EM54 -> 93000 | EP54: 93000 | EQ54: =EO54-EP54 -> 0 | EV54: 製造T | EW54: Plan1.3 | EY54: Plan1.3比 | EZ54: ■新規BPOを中心に積み上げ中 | FE54: 製造 | FH54: Plan1.3比はInfluence抜き
A55: 製造T | B55: Daifuku Co., Ltd. | C55: AIものづくり支援環境構築 | D55: 継続 | E55: 10-12月分受注済。対応中 | F55: 臼井、方 | G55: A | P55: 2851569.1 | Q55: 2050000 | AV55: =3500000*0.2+2500000*0.3+1500000*0.4 -> 2050000 | CB55: =3500000*0.25+1500000*0.55+2500000*0.45 -> 2825000 | DG55: =3500000*0.25+1500000*0.55+2500000*0.45 -> 2825000 | EM55: =3500000*0.25+1500000*0.55+2500000*0.45 -> 2825000 | EO55: =P55+Q55+AV55+CB55+DG55+EM55 -> 15426569 | EP55: 13101569 | EQ55: =EO55-EP55 -> 2325000 | EV55: =SUM(EO54:EO78) -> 63850673 | EW55: =SUM(EP54:EP79) -> 67750673 | EY55: =EV55/EW55 -> 0.942436 | EZ55: 確度 | FA55: 下期 | FB55: Plan | FE55: Plan1.3比 | FF55: =FH61/FI61 -> 0.96081286 | FG55: 確度 | FH55: 下期 | FI55: Plan1.3 | FJ55: 100%KPI
A56: 製造T | B56: Daiwa House | C56: 大和ハウス DTMSカスタマイズ・導入支援 | D56: 新規 | E56: DTMSカスタマイズBPO→失注（保留） | F56: ー | G56: ー | P56: 0 | Q56: 0 | AV56: 0 | CB56: 0 | DG56: 0 | EM56: 0 | EO56: =P56+Q56+AV56+CB56+DG56+EM56 -> 0 | EP56: 0 | EQ56: =EO56-EP56 -> 0 | EW56: =EV55-EW55 -> -3900000 | EZ56: A | FA56: =SUMIF($G$54:$G$78,EZ56,$EO$54:$EO$78) -> 51850673 | FE56: KPI比 | FF56: =FH65/FJ65 -> 0.98382249 | FG56: A | FH56: =SUMIF($G$54:$G$78,FG56,$EO$54:$EO$78)+O77 -> 83622437
A57: 製造T | B57: Daiwa House | C57: 大和ハウス AI支援 | D57: 新規 | E57: 反応なくいったん保留 | F57: ー | G57: ー | AV57: 0 | CB57: 0 | DG57: 0 | EM57: 0 | EO57: =P57+Q57+AV57+CB57+DG57+EM57 -> 0 | EP57: 0 | EQ57: =EO57-EP57 -> 0 | EZ57: B | FA57: =SUMIF($G$54:$G$76,EZ57,$EO$54:$EO$76) -> 0 | FG57: B | FH57: =SUMIF($G$54:$G$76,FG57,$EO$54:$EO$76) -> 0
A58: 製造T | B58: IODATA | C58: PM/PL要員育成ロードマップ作成、教育支援 | D58: 新規 | E58: 予算確保済。担当者変更。来年度以降に再提案 | F58: 臼井 | G58: ー | P58: 0 | Q58: 0 | AV58: 0 | CB58: 0 | DG58: 0 | EM58: 0 | EO58: =P58+Q58+AV58+CB58+DG58+EM58 -> 0 | EP58: 0 | EQ58: =EO58-EP58 -> 0 | EZ58: C | FA58: =SUMIF($G$54:$G$76,EZ58,$EO$54:$EO$76) -> 9300000 | FG58: C | FH58: =SUMIF($G$54:$G$76,FG58,$EO$54:$EO$76) -> 9300000
A59: 製造T | B59: Mitsubishi UFJ Trust System | C59: UiPath開発 | D59: 新規 | E59: 26年4月以降。社内で対応を検討する（ホアンさん対応待ち） | F59: 鷹野、松田 | G59: ー | P59: 0 | Q59: 0 | AV59: 0 | CB59: 0 | DG59: 0 | EM59: 0 | EO59: =P59+Q59+AV59+CB59+DG59+EM59 -> 0 | EP59: 0 | EQ59: =EO59-EP59 -> 0 | EZ59: D | FA59: =SUMIF($G$54:$N$78,EZ59,$EO$54:$EO$76) -> 2700000 | FG59: D | FH59: =SUMIF($G$54:$N$78,FG59,$EO$54:$EO$76) -> 2700000
A60: 製造T | B60: YKK AP Inc. | C60: YKKAP_次期AP-CADシステム刷新_開発フェーズ | D60: 継続 | E60: 11月-12月分（PoC2）を受注。11/10キックオフ・懇親会 | F60: 鷹野、松田 | G60: A | P60: 0 | AV60: 0 | CB60: 0 | DG60: =3700000/2 -> 1850000 | EM60: =3700000/2 -> 1850000 | EO60: =P60+Q60+AV60+CB60+DG60+EM60 -> 3700000 | EP60: 0 | EQ60: =EO60-EP60 -> 3700000 | EZ60: O | FA60: =SUMIF($G$54:$G$74,EZ60,$EO$54:$EO$74) -> 0 | FG60: O | FH60: =SUMIF($G$54:$G$74,FG60,$EO$54:$EO$74) -> 0
A61: 製造T | B61: オリックス銀行株式会社 | C61: RPA運用支援＆akaBot検証 | D61: 新規 | E61: 12月まで契約済。低利益率のため、来年度の対応を要検討 | F61: バンクス、BP | G61: A | P61: 18901.72 | Q61: 2000000 | AV61: 2000000 | CB61: 2500000 | DG61: 2500000 | EM61: 2500000 | EO61: =P61+Q61+AV61+CB61+DG61+EM61 -> 11518902 | EP61: 11518902 | EQ61: =EO61-EP61 -> 0 | ES61: ※7月分調整入っている | EZ61: 合計 | FA61: =SUM(FA56:FA60) -> 63850673 | FB61: 118675000 | FG61: 積上げ | FH61: =SUM(FH56:FH60) -> 95622437 | FI61: 99522437
A62: 製造T | B62: 野村不動産 | C62: 営業支援ツール | D62: 新規 | E62: 稼働中 | F62: 方 | G62: A | P62: 0 | Q62: 0 | AV62: 2764000 | DG62: 0 | EM62: 0 | EO62: =P62+Q62+AV62+CB62+DG62+EM62 -> 2764000 | EP62: 2764000 | EQ62: =EO62-EP62 -> 0
A63: 製造T | B63: 野村不動産 | C63: 営業支援ツール2期 | D63: 新規 | E63: ９月、１０月案件拡大 | F63: 方 | G63: A | Q63: 0 | AV63: 0 | CB63: 2930000 | EM63: 0 | EO63: =P63+Q63+AV63+CB63+DG63+EM63 -> 2930000 | EP63: 2930000 | EQ63: =EO63-EP63 -> 0 | FG63: Influence | FH63: =チーム別PreSales!E6 -> 2759811.4
A64: 製造T | B64: LIXIL | C64: BPO業務自動化支援 | D64: 新規 | E64: 10月分までは完了 | F64: 鷹野、松田 | G64: A | P64: 0 | Q64: 1800000 | AV64: 1800000 | CB64: 1800000 | EO64: =P64+Q64+AV64+CB64+DG64+EM64 -> 5400000 | EP64: 5400000 | EQ64: =EO64-EP64 -> 0
A65: 製造T | B65: LIXIL | C65: BPO業務自動化支援 | D65: 継続 | E65: 11月以降分を調整中 | F65: 鷹野、松田 | G65: C | P65: 0 | DG65: 3000000 | EM65: 3000000 | EO65: =P65+Q65+AV65+CB65+DG65+EM65 -> 6000000 | EP65: 6000000 | EQ65: =EO65-EP65 -> 0 | FG65: 見込合計 | FH65: =FH61+FH63 -> 98382249 | FJ65: 100000000
A66: 製造T | B66: DKI（ダイキン情報システム） | C66: akaBot支援 | D66: 新規 | E66: 7/3訪問、打合せ→保留 | F66: ー | G66: ー | P66: 0 | Q66: 0 | AV66: 0 | CB66: 0 | DG66: 0 | EM66: 0 | EO66: =P66+Q66+AV66+CB66+DG66+EM66 -> 0 | EP66: 0 | EQ66: =EO66-EP66 -> 0
A67: 製造T | B67: ヤンマー | C67: PLM(Windchill）周辺システム開発 | D67: 新規 | E67: 11月開始が遅れ。GMGと調整中 | F67: ー | G67: D | P67: 0 | Q67: 0 | AV67: 0 | CB67: 0 | DG67: =600000+1500000*0.5 -> 1350000 | EM67: =600000+1500000*0.5 -> 1350000 | EO67: =P67+Q67+AV67+CB67+DG67+EM67 -> 2700000 | EP67: 2700000 | EQ67: =EO67-EP67 -> 0
A68: 製造T | B68: Siemens | C68: NX/Teamcenter支援（バルミューダ） | D68: 新規 | E68: ライセンス売上計上。その他バルミューダから有償技術支援の相談があり、調整中 | F68: ー | G68: A | P68: 0 | Q68: 0 | AV68: 1093202 | CB68: 0 | DG68: 0 | EM68: 0 | EO68: =P68+Q68+AV68+CB68+DG68+EM68 -> 1093202 | EP68: 1093202 | EQ68: =EO68-EP68 -> 0 | EY68: 下期 | FE68: チーム合計 | FH68: Plan1.3比はInfluence込み
A69: 製造T | B69: アウトソーシング | C69: 人材派遣 提案支援 | D69: 新規 | E69: 6/27提案書提出 →ロスト（Sun Astrriskが受注） | F69: ー | G69: ー | P69: 0 | Q69: 0 | EO69: =P69+Q69+AV69+CB69+DG69+EM69 -> 0 | EP69: 0 | EQ69: =EO69-EP69 -> 0 | EY69: =FA77/FB77 -> 1.4121992 | EZ69: 確度 | FA69: 下期 | FB69: Plan1.3 | FE69: Plan1.3比 | FF69: =FH80/FI80 -> 0.98005224 | FG69: 確度 | FH69: 下期 | FI69: Plan1.3 | FJ69: 100%KPI
A70: 製造T | B70: ダイキン | C70: グローバルデータ基盤構築 | D70: 継続 | E70: 2026年4月以降にインプリ提案。下期も案件ないかを相談する | F70: 臼井 | G70: ー | P70: 0 | AV70: 0 | EO70: =P70+Q70+AV70+CB70+DG70+EM70 -> 0 | EP70: 0 | EQ70: =EO70-EP70 -> 0 | EZ70: A | FA70: =FA6+FA30+FA56 -> 2.762004e+08 | FE70: KPI比 | FF70: =FH80/FJ81 -> 1.1712839 | FG70: A | FH70: =FH6+FH30+FH56 -> 4.1491302e+08
A71: 製造T | B71: ダイキン | C71: PLMコンサル | D71: 継続 | E71: 稼働中。10-11月受注済。対応中 | F71: 臼井、BP | G71: A | P71: 0 | Q71: 800000 | AV71: =3500000*0.1+3000000*0.15 -> 800000 | CB71: =1300000 -> 1300000 | DG71: =1300000 -> 1300000 | EO71: =P71+Q71+AV71+CB71+DG71+EM71 -> 4200000 | EP71: 4000000 | EQ71: =EO71-EP71 -> 200000 | EZ71: B | FA71: =FA7+FA31+FA57 -> 6490000 | FG71: B | FH71: =FH7+FH31+FH57 -> 6490000
A72: 製造T | B72: ダイキン | C72: PLMコンサル | D72: 継続 | E72: 12月継続提案（11月中） | F72: 臼井、BP | G72: C | P72: 0 | EM72: =3500000*0.1+3000000*0.15 -> 800000 | EO72: =P72+Q72+AV72+CB72+DG72+EM72 -> 800000 | EQ72: =EO72-EP72 -> 800000 | EZ72: B | FA72: =FA8+FA32+FA58 -> 9960000 | FG72: C | FH72: =FH8+FH32+FH58 -> 9960000
A73: 製造T | B73: DNP | C73: DNPのBPO業務 | D73: 新規 | E73: 提案先組織変更で再調整 | F73: 鷹野、川口、BP | G73: ー | P73: 0 | Q73: 0 | AV73: 0 | EO73: =P73+Q73+AV73+CB73+DG73+EM73 -> 0 | EP73: 0 | EQ73: =EO73-EP73 -> 0 | EZ73: C | FA73: =FA8+FA32+FA58 -> 9960000 | FG73: D | FH73: =FH9+FH33+FH59 -> 2700000
A74: 製造T | B74: SCSK | C74: BPR案件、DXチームからの引継ぎ。 | D74: 継続 | E74: 10月分までは完了 | F74: 臼井、松田 | G74: A | P74: 0 | Q74: 775000 | AV74: 775000 | CB74: 775000 | EO74: =P74+Q74+AV74+CB74+DG74+EM74 -> 2325000 | EQ74: =EO74-EP74 -> 2325000 | EZ74: D | FA74: =FA9+FA33+FA59 -> 2700000 | FG74: D | FH74: =FH10+FH34+FH60 -> 0
A75: 製造T | B75: SCSK | C75: BPR案件、DXチームからの引継ぎ。 | D75: 継続 | E75: 稼働中。11/6に最終報告会、次期提案予定 | F75: 臼井、松田 | G75: C | P75: 0 | DG75: 1250000 | EM75: 1250000 | EO75: =P75+Q75+AV75+CB75+DG75+EM75 -> 2500000 | EP75: 6250000 | EQ75: =EO75-EP75 -> -3750000 | EZ75: D | FA75: =FA10+FA34+FA60 -> 0 | FG75: O | FH75: =FH10+FH34+FH60 -> 0
A76: 製造T | B76: ITEC阪急阪神 | C76: i-PLAT調査、導入支援 | D76: 新規 | E76: 2500万、コンサル1140万円、10月中旬開始予定→9/30失注 | F76: 鷹野、松田 | G76: ー | P76: 0 | Q76: 0 | AV76: 0 | CB76: 0 | DG76: 0 | EM76: 0 | EO76: =P76+Q76+AV76+CB76+DG76+EM76 -> 0 | EP76: 9500000 | EQ76: =EO76-EP76 -> -9500000 | EZ76: O | FA76: =FA10+FA34+FA60 -> 0 | FG76: 積上げ | FH76: =SUM(FH70:FH75) -> 4.3406302e+08 | FI76: 4.6683577e+08
A77: 製造T | B77: 実績積みあげ | I77: 5564550 | J77: 4550400 | K77: 7070449.5 | L77: 1831287.5 | M77: 6842527.5 | N77: 5912550 | O77: =SUM(I77:N77) -> 31771765 | EZ77: 合計 | FA77: =SUM(FA70:FA76) -> 3.053104e+08 | FB77: =FB11+FB35+FB61 -> 216195000
A78: 製造T | B78: KMI | C78: KMI_コンカレントECM | D78: 新規 | E78: 稼働中。マレーシアの生産拠点DXをテーマに打合せ | F78: 臼井 | G78: A | P78: 0 | Q78: 0 | AV78: 600000 | CB78: 600000 | DG78: 600000 | EM78: 600000 | EO78: =P78+Q78+AV78+CB78+DG78+EM78 -> 2400000 | EP78: 2400000 | EQ78: =EO78-EP78 -> 0 | FG78: Influence | FH78: =チーム別PreSales!E7 -> 34450540 | FI78: 11213805
A79: 製造T | B79: ELECOM | C79: SSC PoC開発支援 | D79: 新規 | E79: 10/1提案→10/6内示。10/16プロジェクト開始 | F79: 臼井 | G79: A | P79: 0 | Q79: 0 | AV79: 0 | CB79: 1300000 | CC79: 2100000 | CD79: 1950000 | DG79: =6650000/5*2 -> 2660000 | EM79: =6650000/5*2 -> 2660000 | EO79: =P79+Q79+AV79+CB79+DG79+EM79 -> 6620000 | EP79: 0 | EQ79: =EO79-EP79 -> 6620000
A80: 製造T | B80: SB C&S（ICT事業本部） | C80: SB C&S（ICT事業本部） | D80: 新規 | E80: 10/6提案書送付済（947～1280万円。松竹梅の見積提示）提案書提出済 | G80: D | FG80: 見込合計 | FH80: =FH76+FH78 -> 4.6851356e+08 | FI80: =FI76+FI78 -> 4.7804958e+08
A81: 製造T | B81: SB C&S（田中ICO/情シス本部長） | C81: SB C&S（田中ICO/情シス本部長） | D81: 新規 | E81: 10/6週以降でRFPを受領予定。提案書提出済 | G81: D | FJ81: 400000000
A82: 業務ITT | B82: デロイト協業（Akila） | C82: デロイト協業（Akila） | D82: 新規 | E82: 10/17：NDA締結中 | G82: O
A83: 業務改善T | B83: デロイト協業（基幹） | C83: デロイト協業（基幹） | D83: 新規 | E83: 10/17：NDA締結中 | G83: O
A84: 製造T | B84: オムロン | C84: オムロン | D84: 新規 | G84: O
A85: 製造T | B85: シマノ | C85: シマノ | D85: 新規 | E85: 役員への提案からなので案件化には時間がかかるFY26案件か | G85: O
A86: 製造T | B86: 竹中工務店関連1 | C86: AI戦略策定 | D86: 新規 | E86: 八巻さんTからの紹介 | G86: O
A87: 製造T | B87: 竹中工務店関連2 | C87: AI戦略策定 | D87: 新規 | E87: 八巻さんTからの紹介 | G87: O

Sheet FY26フォロー状況
A1: サブチーム | B1: クライアント名 | C1: PJ名 | E1: コメント | F1: メンバ | G1: 確度 | H1: 粗利率 | J1: 11月見込 | K1: 12月見込 | L1: 1月 | M1: 2月 | N1: 3月 | O1: 4月 | P1: 5月 | Q1: 6月 | R1: 7月 | S1: 8月 | T1: 9月 | U1: 10月 | V1: 11月 | W1: 12月 | Y1: 通期 | Z1: Plan1.0 | AA1: Plan1.0比 | AM1: ■Opp Stage定義
I2: 67657800 | J2: 60518100 | K2: 58018250 | X2: Revenue合計 | Y2: =AI78 -> #REF! | Z2: 4.7804958e+08 | AA2: =Y2/Z2 -> #REF! | AF2: FY25 通期 | AN2: 区分 | AO2: 受注確率 | AP2: 入れる内容例
X3: Influence | Y3: =AI76 -> 0 | Z3: =AJ76 -> 0 | AA3: =Y3/Z3 -> #DIV/0!
B4: FY25NewLogo | I4: =SUM(I5:I75) -> 51660000 | J4: =SUM(J5:J75) -> 53455000 | K4: =SUM(K5:K75) -> 56990000 | X4: 下期積上 | Y4: =SUM(Y5:Y88) -> 0 | Z4: 3.2395067e+08 | AA4: =Y4/Z4 -> 0 | AF4: 業務IT | AI4: Plan1.0比はInfluence抜き | AN4: O | AO4: 20%以下 | AP4: 白地のもの。オポチュニティーを認識したレベル。
A5: 業務ITT | B5: JSOL Corporation | C5: BIM汎用コンポーネント開発支援 | D5: 継続 | E5: 稼働中 | F5: 中村、天野、田村 | G5: A | H5: 0.57 | I5: 1700000 | J5: 0 | K5: 0 | Y5: =SUM(L5:X5) -> 0 | AA5: =Y5-Z5 -> 0 | AF5: Plan1.0比 | AG5: =AI11/AJ11 -> #REF! | AH5: 確度 | AI5: 下期 | AJ5: Plan1.0 | AK5: 100%KPI | AN5: D | AO5: 0.5 | AP5: 提案実施済み、もしくは提案実施までは決まっているが受注可否が未定。
A6: 業務ITT | B6: NISHIMATSU CONSTRUCTION CO.,LTD. | C6: BIMモデリング支援 | D6: 継続 | E6: 稼働中（11,12月も継続予定） | F6: 中村 | G6: A | H6: 0.57 | I6: 750000 | J6: 750000 | K6: 750000 | Y6: =SUM(L6:X6) -> 0 | AA6: =Y6-Z6 -> 0 | AF6: KPI比 | AG6: =AI15/AK15 -> #REF! | AH6: A | AI6: =SUMIF($G$5:$G$27,"A",$Y$5:$Y$27)+#REF! -> #REF! | AN6: C | AO6: 0.8 | AP6: A or Bの案件テーマの継続だが、まだ契約を実施していない。ただほぼ受注は問題ない案件。
A7: 業務ITT | B7: SHIMZ | C7: FM事業支援 | D7: 新規 | E7: 稼働中 | F7: 八巻、趙 | G7: A | H7: 0.46 | I7: 500000 | J7: 500000 | K7: 500000 | Y7: =SUM(L7:X7) -> 0 | AA7: =Y7-Z7 -> 0 | AH7: B | AI7: =SUMIF($G$5:$G$27,"B",$Y$5:$Y$27) -> 0 | AN7: B | AO7: 0.99 | AP7: 受注したが契約が未締結。
A8: 業務ITT | B8: Takenaka Corporation | C8: BIM基盤構築（3-7月）※コンサル | D8: 継続 | E8: 稼働中 | F8: 八巻、田口、益田、趙、加賀谷 | G8: A | H8: 0.25 | I8: 0 | J8: 0 | K8: 0 | Y8: =SUM(L8:X8) -> 0 | AA8: =Y8-Z8 -> 0 | AH8: C | AI8: =SUMIF($G$5:$G$27,"C",$Y$5:$Y$27) -> 0 | AN8: A | AO8: 1 | AP8: 受注確定し、契約も実施。
A9: 業務ITT | B9: Takenaka Corporation | C9: BIM基盤構築（8-12月）※コンサル | D9: 継続 | E9: 稼働中 | F9: 八巻、田口、益田、趙、BP | G9: A | H9: 0.25 | I9: 8480000 | J9: 8480000 | K9: 8480000 | Y9: =SUM(L9:X9) -> 0 | AA9: =Y9-Z9 -> 0 | AH9: D | AI9: =SUMIF($G$5:$G$27,"D",$Y$5:$Y$27) -> 0
A10: 業務ITT | B10: Takenaka Corporation | C10: 大阪本店 Akila導入検証 | D10: 新規 | E10: 提案見積提出済み（動きなし） | F10: 八巻、趙 | G10: ー | I10: 0 | J10: 0 | K10: 0 | Y10: =SUM(L10:X10) -> 0 | AA10: =Y10-Z10 -> 0 | AH10: O | AI10: =SUMIF($G$5:$G$27,"o",$Y$5:$Y$27) -> 0
A11: 業務ITT | B11: Takenaka Corporation | C11: 中央監視システム開発支援 | D11: 新規 | E11: 提案見積提出済み（動きなし） | F11: 八巻、田口 | G11: ー | I11: 0 | J11: 0 | K11: 0 | Y11: =SUM(L11:X11) -> 0 | AA11: =Y11-Z11 -> 0 | AH11: 積上げ | AI11: =SUM(AI6:AI10) -> #REF! | AJ11: 147703032
A12: 業務ITT | B12: New Customer（大林組） | C12: デジタルツイン（Akila PoCプラン） | D12: 新規 | E12: 10/17現調実施。11月契約12月稼働開始で調整中（12月～2月） | F12: 八巻、天野 | G12: C | I12: 0 | J12: 0 | K12: 280000 | Y12: =SUM(L12:X12) -> 0 | AA12: =Y12-Z12 -> 0
A13: 業務ITT | B13: DAISUE CONSTRUCTION CO.,LTD. | C13: BIM動画作成（下期） | D13: 継続 | E13: 12月建設DX展に合わせて実施 | F13: 中村 | G13: A | K13: 175000 | Y13: =SUM(L13:X13) -> 0 | AA13: =Y13-Z13 -> 0 | AH13: Influence | AI13: =チーム別PreSales!E4 -> 30956700
A14: 業務ITT | B14: JSOL Corporation | C14: 建設DXコンサル支援（ナカノフドー建設） | D14: 新規 | E14: 稼働中（～2026年3月） | F14: 中村、天野 | G14: A | H14: 0.49 | I14: 1960000 | J14: 1960000 | K14: 1960000 | Y14: =SUM(L14:X14) -> 0 | AA14: =Y14-Z14 -> 0
A15: 業務ITT | B15: DAISUE CONSTRUCTION CO.,LTD. | C15: BIM品質チェックリスト作成協力業務 | D15: 新規 | E15: 完了 | F15: 中村 | G15: A | I15: 0 | J15: 0 | K15: 0 | Y15: =SUM(L15:X15) -> 0 | AA15: =Y15-Z15 -> 0 | AH15: 見込合計 | AI15: =AI11+AI13 -> #REF! | AK15: 106000000
A16: 業務ITT | B16: New Customer（JR東日本建築設計） | C16: デジタルツイン（Akila PoCプラン） | D16: 新規 | E16: 7/1提案、動きなし。 | F16: 八巻 | G16: ー | Y16: =SUM(L16:X16) -> 0 | AA16: =Y16-Z16 -> 0
A17: 業務ITT | B17: New Customer（清水建設） | C17: デジタルツイン（Akila PoCプラン） | D17: 新規 | E17: 8/29見積提出、動きなし。 | F17: 八巻 | G17: ー | Y17: =SUM(L17:X17) -> 0 | AA17: =Y17-Z17 -> 0
A18: 業務ITT | B18: New Customer（長谷工） | C18: デジタルツイン（Akila PoCプラン） | D18: 新規 | E18: 6/26会社紹介 | F18: 八巻 | G18: ー | Y18: =SUM(L18:X18) -> 0 | AA18: =Y18-Z18 -> 0
A19: 業務ITT | B19: New Customer（住友商事） | C19: デジタルツイン（Akila PoCプラン） | D19: 新規 | E19: BCOアポ取り中 | F19: 八巻 | G19: ー | Y19: =SUM(L19:X19) -> 0 | AA19: =Y19-Z19 -> 0
A20: 業務ITT | B20: New Customer（ファーストリテイリング） | C20: デジタルツイン（Akila PoCプラン） | D20: 新規 | E20: BCOアポ取り中 | F20: 八巻 | G20: ー | Y20: =SUM(L20:X20) -> 0 | AA20: =Y20-Z20 -> 0
A21: 業務ITT | B21: New Customer（ニトリ） | C21: デジタルツイン（Akila PoCプラン） | D21: 新規 | E21: BCOアポ取り中 | F21: 八巻 | G21: ー | Y21: =SUM(L21:X21) -> 0 | AA21: =Y21-Z21 -> 0
A22: 業務ITT | B22: New Customer（資生堂） | C22: デジタルツイン（Akila PoCプラン） | D22: 新規 | E22: BCOアポ取り中 | F22: 八巻 | G22: ー | Y22: =SUM(L22:X22) -> 0 | AA22: =Y22-Z22 -> 0
A23: 業務ITT | B23: Takenaka Corporation | C23: BIM基盤構築（開発） | D23: 継続 | E23: 稼働中（～2026年12月） | F23: 田口 | G23: A | H23: 0.25 | I23: 2000000 | J23: 2000000 | K23: 2000000 | Y23: =SUM(L23:X23) -> 0 | AA23: =Y23-Z23 -> 0
A24: 業務ITT | B24: JSOL Corporation | C24: 建設DXコンサル支援（ピーエスコンストラクション） | D24: 新規 | E24: 稼働中（～2026年3月） | F24: 八巻、田村 | G24: A | H24: 0.49 | I24: 1880000 | J24: 1880000 | K24: 1880000 | Y24: =SUM(L24:X24) -> 0 | AA24: =Y24-Z24 -> 0
A25: 業務ITT | B25: DAISUE CONSTRUCTION CO.,LTD. | C25: 3Dでの整合性確認の事例紹介の動画作成業務 | D25: 新規 | E25: 完了 | F25: 中村、久保田 | G25: A | Y25: =SUM(L25:X25) -> 0 | AA25: =Y25-Z25 -> 0
A26: 業務ITT | B26: 実績積みあげ | Y26: =SUM(L26:X26) -> 0
A27: 業務ITT | B27: Takenaka Corporation | C27: DLM基盤構築（開発） | D27: 新規 | E27: 稼働中（～2026年12月） | F27: 千葉 | G27: A | H27: 0.2 | I27: 2000000 | J27: 2000000 | K27: 2000000 | Y27: =SUM(L27:X27) -> 0 | AA27: =Y27-Z27 -> 0 | AF27: FY25 通期
A28: 業務改善T | B28: Asunaro Aoki Construction Co.,Ltd. | C28: AAK_スマートBPO業務・方針整理（1月～9月） | D28: 継続 | E28: 稼働中 | F28: 又地、石川、平塚、京地 | G28: A | H28: 0.54 | I28: 0 | J28: 0 | K28: 0 | Y28: =SUM(L28:X28) -> 0 | AA28: =Y28-Z28 -> 0 | AF28: 業務改善 | AI28: Plan1.0比はInfluence抜き
A29: 業務改善T | B29: Asunaro Aoki Construction Co.,Ltd. | C29: AAK_スマートBPO業務・方針整理（10月～12月） | D29: 継続 | E29: 受注確定：契約手続き中 | F29: 又地、石川、平塚、京地 | G29: A | I29: 2100000 | J29: 2100000 | K29: 2100000 | Y29: =SUM(L29:X29) -> 0 | AA29: =Y29-Z29 -> 0 | AF29: Plan1.0比 | AG29: =AI35/AJ35 -> #REF! | AH29: 確度 | AI29: 下期 | AJ29: Plan1.0 | AK29: 100%KPI
A30: 業務改善T | B30: Asunaro Aoki Construction Co.,Ltd. | C30: 業務改善（1月～9月） | D30: 継続 | E30: 稼働中 | F30: 又地、石川、平塚、京地 | G30: A | H30: 0.37 | I30: 0 | J30: 0 | K30: 0 | Y30: =SUM(L30:X30) -> 0 | AA30: =Y30-Z30 -> 0 | AF30: KPI比 | AG30: =AI39/AK39 -> #REF! | AH30: A | AI30: =SUMIF($G$28:$G$52,AH30,$Y$28:$Y$52)+#REF!+#REF! -> #REF!
A31: 業務改善T | B31: Asunaro Aoki Construction Co.,Ltd. | C31: 業務改善（10月～12月） | D31: 継続 | E31: 受注確定：契約手続き中 | F31: 又地、石川、平塚、京地 | G31: A | I31: 2250000 | J31: 2250000 | K31: 1500000 | Y31: =SUM(L31:X31) -> 0 | AA31: =Y31-Z31 -> 0 | AH31: B | AI31: =SUMIF($G$28:$G$52,AH31,$Y$28:$Y$52) -> 0
A32: 業務改善T | B32: DAISUE CONSTRUCTION CO.,LTD. | C32: [Renew] DX system AMS phase（1月～9月） | D32: 継続 | E32: 稼働中 | F32: 中村、久保田 | G32: A | I32: 0 | J32: 0 | K32: 0 | Y32: =SUM(L32:X32) -> 0 | AA32: =Y32-Z32 -> 0 | AH32: C | AI32: =SUMIF($G$28:$G$52,AH32,$Y$28:$Y$52) -> 0
A33: 業務改善T | B33: DAISUE CONSTRUCTION CO.,LTD. | C33: [Renew] DX system AMS phase（10月～12月） | D33: 継続 | E33: 受注確定：契約手続き中 | F33: 中村、久保田 | G33: A | I33: 750000 | J33: 750000 | K33: 750000 | Y33: =SUM(L33:X33) -> 0 | AA33: =Y33-Z33 -> 0 | AH33: D | AI33: =SUMIF($G$28:$G$52,AH33,$Y$28:$Y$52) -> 0
A34: 業務改善T | B34: DAISUE CONSTRUCTION CO.,LTD. | C34: DXS-2 | D34: 継続 | E34: 先方リソース不足により当初の予定より遅延。開始に向けて請求外支援中 | F34: 加藤、久保田 | G34: - | I34: 0 | J34: 0 | K34: 0 | Y34: =SUM(L34:X34) -> 0 | AA34: =Y34-Z34 -> 0 | AH34: O | AI34: =SUMIF($G$28:$G$52,AH34,$Y$28:$Y$52) -> 0
A35: 業務改善T | B35: DAISUE CONSTRUCTION CO.,LTD. | C35: ラクタス新規開発（DXS２遅延の穴埋め） | D35: 新規 | E35: 10月スタートで提案書最終版提出済み。確定待ち | F35: 加藤、久保田 | G35: A | I35: 600000 | J35: 600000 | K35: 0 | Y35: =SUM(L35:X35) -> 0 | AA35: =Y35-Z35 -> 0 | AH35: 積上げ | AI35: =SUM(AI30:AI34) -> #REF! | AJ35: 209139818
A36: 業務改善T | B36: DAISUE CONSTRUCTION CO.,LTD. | C36: 基幹システムリプレイス（1月～9月） | D36: 継続 | E36: 稼働中 | F36: 加藤、多ケ谷 | G36: A | H36: 0.37 | I36: 0 | J36: 0 | K36: 0 | Y36: =SUM(L36:X36) -> 0 | AA36: =Y36-Z36 -> 0
A37: 業務改善T | B37: DAISUE CONSTRUCTION CO.,LTD. | C37: 基幹システムリプレイス（10月～12月） | D37: 継続 | E37: 受注ほぼ確定：当初より150万程度の増額、先方社内で稟申中。確定待ち | F37: 加藤、多ケ谷 | G37: A | I37: 11660000 | J37: 11660000 | K37: 10540000 | Y37: =SUM(L37:X37) -> 0 | AA37: =Y37-Z37 -> 0 | AH37: Influence | AI37: =チーム別PreSales!E5 -> 734028.75
A38: 業務改善T | B38: アプリ展開①：鍜治田工務店（大末横展開） | C38: DXS展開 | D38: 新規 | E38: 7/17に三田来訪。協議継続中。次回は9月。来期予算取り | F38: 加藤 | G38: ー | I38: 0 | J38: 0 | K38: 0 | Y38: =SUM(L38:X38) -> 0 | AA38: =Y38-Z38 -> 0
A39: 業務改善T | B39: アプリ展開②：りんかい日産建設他（大末横展開） | C39: DXS展開 | D39: 新規 | E39: 大末からの横展開が困難、個別アポどり難航。TCG基幹次第で中断する方針 | F39: 加藤 | G39: ー | I39: 0 | J39: 0 | K39: 0 | Y39: =SUM(L39:X39) -> 0 | AA39: =Y39-Z39 -> 0 | AH39: 見込合計 | AI39: =AI35+AI37 -> #REF! | AK39: 160000000
A40: 業務改善T | B40: アプリ展開③：錢高組他（大末横展開） | C40: DXS展開 | D40: 新規 | E40: 大末からの横展開が困難、個別アポどり難航。TCG基幹次第で中断する方針 | F40: 加藤 | G40: ー | I40: 0 | J40: 0 | K40: 0 | Y40: =SUM(L40:X40) -> 0 | AA40: =Y40-Z40 -> 0
A41: 業務改善T | B41: 髙松コンストラクショングループ | C41: 基幹：業務調査・要件整理・RFPのネタ作成 | D41: 新規 | E41: 提案4回、最有力だが先方意思決定難航。PJTはAA主管、コンサル選定はTCGとのこと。望月社長経由でのプッシュ継続。 | F41: 加藤 | G41: ー | I41: 0 | J41: 0 | K41: 0 | Y41: =SUM(L41:X41) -> 0 | AA41: =Y41-Z41 -> 0
A42: 業務改善T | B42: 東興ジオテック | C42: 業務調査、要件整理 | D42: 新規 | E42: AA望月社長からの紹介、10/6提案、ほぼ確定。先方稟申中。10/20TEL予定 | F42: 加藤、境 | G42: C | I42: 0 | J42: 2500000 | K42: 5100000 | Y42: =SUM(L42:X42) -> 0 | AA42: =Y42-Z42 -> 0
A43: 業務改善T | B43: Asunaro Aoki Construction Co.,Ltd. | C43: 水中ブルドーザー市場調査 | D43: 新規 | E43: 望月様紹介により土木事業部の市場調査を受注 | F43: 瀬田、又地、田村 | G43: A | H43: 0.55 | I43: 0 | J43: 0 | K43: 0 | Y43: =SUM(L43:X43) -> 0 | AA43: =Y43-Z43 -> 0
A44: 業務改善T | B44: Asunaro Aoki Construction Co.,Ltd. | C44: 水中ブルドーザービジネス支援 | D44: 継続 | E44: 市場調査後の、各種資料作成・PMO 11月～1月 3か月 105万円×3 | F44: 又地 | G44: B | I44: 0 | J44: 1050000 | K44: 1050000 | Y44: =SUM(L44:X44) -> 0 | AA44: =Y44-Z44 -> 0
A45: 業務改善T | B45: Asunaro Aoki Construction Co.,Ltd. | C45: データセンター市場調査 | D45: 継続 | E45: 市場調査後の、各種資料作成・PMO。10/24頃までには判明？ | F45: 加藤、又地 | G45: - | I45: 0 | J45: 0 | K45: 0 | Y45: =SUM(L45:X45) -> 0 | AA45: =Y45-Z45 -> 0
A46: 業務改善T | B46: Asunaro Aoki Construction Co.,Ltd. | C46: GX市場調査 | D46: 新規 | E46: 水中ブルドーザー市場調査を評価頂き更に別件の土木の市場調査を受注 | F46: 瀬田、又地、境 | G46: A | I46: 2300000 | J46: 0 | K46: 0 | Y46: =SUM(L46:X46) -> 0 | AA46: =Y46-Z46 -> 0
A47: 業務改善T | B47: Asunaro Aoki Construction Co.,Ltd. | C47: 経営管理システム構築 | D47: 新規 | E47: 基幹刷新に伴うAA周辺システムの構築 | F47: 加藤、京地 | G47: D | J47: 0 | K47: 2450000 | Y47: =SUM(L47:X47) -> 0 | AA47: =Y47-Z47 -> 0
A48: 業務改善T | B48: 野村不動産 | C48: 財務諸表統合BI | D48: 新規 | E48: 10月11月 ※金額はこれから | F48: 多ケ谷 | G48: B | I48: 0 | K48: 1000000 | Y48: =SUM(L48:X48) -> 0 | AA48: =Y48-Z48 -> 0
A49: 業務改善T | B49: 野村不動産 | C49: 海外案件管理システム | D49: 新規 | E49: 12月に入るかもしれないが基本は1月以降、コンペとのこと | F49: 多ケ谷 | G49: - | I49: 0 | J49: 0 | K49: 0 | Y49: =SUM(L49:X49) -> 0 | AA49: =Y49-Z49 -> 0
A50: 業務改善T | B50: LIXIL | C50: AIOCR | D50: 新規 | E50: 多ケ谷さん提案継続。11月から0.1程度で支援開始、結果待ち→確度低下 | F50: 多ケ谷 | G50: D | I50: 0 | J50: 300000 | K50: 300000 | Y50: =SUM(L50:X50) -> 0 | AA50: =Y50-Z50 -> 0
A51: 業務改善T | B51: 実績積みあげ | Y51: =SUM(L51:X51) -> 0
A52: 業務改善T | B52: LIXIL | C52: 深谷工場運用保守 | D52: 新規 | E52: FSJにて対応している案件が炎上、管理者として多ケ谷さんが少ない稼働で入る。8月開始 | F52: 多ケ谷 | G52: ー | Y52: =SUM(L52:X52) -> 0 | AA52: =Y52-Z52 -> 0 | AF52: FY25 通期
A53: 製造T | B53: Daifuku Co., Ltd. | C53: 3D CADチェックツール開発(第二弾) | D53: 継続 | E53: 7/15見積送付済。発注待ち | F53: 川口 | G53: A | I53: 0 | J53: 0 | K53: 0 | Y53: =SUM(L53:X53) -> 0 | AA53: =Y53-Z53 -> 0 | AF53: 製造 | AI53: Plan1.0比はInfluence抜き
A54: 製造T | B54: Daifuku Co., Ltd. | C54: AIものづくり支援環境構築 | D54: 継続 | E54: 継続対応中（9月分まで受注済）10月以降提案準備 | F54: 臼井、方 | G54: A | I54: =3500000*0.25+1500000*0.55+2500000*0.45 -> 2825000 | J54: =3500000*0.25+1500000*0.55+2500000*0.45 -> 2825000 | K54: =3500000*0.25+1500000*0.55+2500000*0.45 -> 2825000 | Y54: =SUM(L54:X54) -> 0 | AA54: =Y54-Z54 -> 0 | AF54: Plan1.0比 | AG54: =AI60/AJ60 -> #REF! | AH54: 確度 | AI54: 下期 | AJ54: Plan1.0 | AK54: 100%KPI
A55: 製造T | B55: Daiwa House | C55: 大和ハウス DTMSカスタマイズ・導入支援 | D55: 新規 | E55: DTMSカスタマイズBPO→失注（保留） | F55: ー | G55: ー | I55: 0 | J55: 0 | K55: 0 | Y55: =SUM(L55:X55) -> 0 | AA55: =Y55-Z55 -> 0 | AF55: KPI比 | AG55: =AI64/AK64 -> #REF! | AH55: A | AI55: =SUMIF($G$53:$G$75,AH55,$Y$53:$Y$75)+#REF! -> #REF!
A56: 製造T | B56: Daiwa House | C56: 大和ハウス AI支援 | D56: 新規 | E56: NDA締結し、PoC提案中 | F56: ー | G56: ー | I56: 0 | J56: 0 | K56: 0 | Y56: =SUM(L56:X56) -> 0 | AA56: =Y56-Z56 -> 0 | AH56: B | AI56: =SUMIF($G$53:$G$73,AH56,$Y$53:$Y$73) -> 0
A57: 製造T | B57: IODATA | C57: PM/PL要員育成ロードマップ作成、教育支援 | D57: 新規 | E57: 予算確保済。担当者変更。後任と10/2打合せ | F57: 臼井 | G57: ー | I57: 0 | J57: 0 | K57: 0 | Y57: =SUM(L57:X57) -> 0 | AA57: =Y57-Z57 -> 0 | AH57: C | AI57: =SUMIF($G$53:$G$73,AH57,$Y$53:$Y$73) -> 0
A58: 製造T | B58: Mitsubishi UFJ Trust System | C58: UiPath開発 | D58: 新規 | E58: 7/7見積提示済。10月開始予定（他社UiPath案件が先行しそう） | F58: 鷹野、松田 | G58: ー | I58: 0 | J58: 0 | K58: 0 | Y58: =SUM(L58:X58) -> 0 | AA58: =Y58-Z58 -> 0 | AH58: D | AI58: =SUMIF($G$53:$Q$75,AH58,$Y$53:$Y$73) -> 0
A59: 製造T | B59: YKK AP Inc. | C59: YKKAP_次期AP-CADシステム刷新_開発フェーズ | D59: 継続 | E59: 体制変更でYKKAP社内稟議 受注 | F59: 鷹野、松田 | G59: B | I59: 0 | J59: =3700000/2 -> 1850000 | K59: =3700000/2 -> 1850000 | Y59: =SUM(L59:X59) -> 0 | AA59: =Y59-Z59 -> 0 | AH59: O | AI59: =SUMIF($G$53:$G$72,AH59,$Y$53:$Y$72) -> 0
A60: 製造T | B60: オリックス銀行株式会社 | C60: RPA運用支援＆akaBot検証 | D60: 新規 | E60: 対応中（9月分まで受注済）増員提案実施 | F60: バンクス、BP | G60: A | I60: 2500000 | J60: 2500000 | K60: 2500000 | Y60: =SUM(L60:X60) -> 0 | AA60: =Y60-Z60 -> 0 | AH60: 積上げ | AI60: =SUM(AI55:AI59) -> #REF! | AJ60: 99522437
A61: 製造T | B61: 野村不動産 | C61: 営業支援ツール | D61: 新規 | E61: 稼働中 | F61: 方 | G61: A | J61: 0 | K61: 0 | Y61: =SUM(L61:X61) -> 0 | AA61: =Y61-Z61 -> 0
A62: 製造T | B62: 野村不動産 | C62: 営業支援ツール2期 | D62: 新規 | E62: ９月、１０月案件拡大 | F62: 方 | G62: A | I62: 2930000 | K62: 0 | Y62: =SUM(L62:X62) -> 0 | AA62: =Y62-Z62 -> 0 | AH62: Influence
A63: 製造T | B63: LIXIL | C63: BPO業務自動化支援 | D63: 新規 | E63: 受注確定。8-10月の体制と正式見積準備中。8月着手 | F63: 鷹野、松田 | G63: A | I63: 1800000 | Y63: =SUM(L63:X63) -> 0 | AA63: =Y63-Z63 -> 0
A64: 製造T | B64: LIXIL | C64: BPO業務自動化支援 | D64: 継続 | E64: 11月以降の継続、オフショア分減額 | F64: 鷹野、松田 | G64: C | J64: 3000000 | K64: 3000000 | Y64: =SUM(L64:X64) -> 0 | AA64: =Y64-Z64 -> 0 | AH64: 見込合計 | AI64: =AI60+AI62 -> #REF! | AK64: 100000000
A65: 製造T | B65: DKI（ダイキン情報システム） | C65: akaBot支援 | D65: 新規 | E65: 7/3訪問、打合せ→保留 | F65: ー | G65: ー | I65: 0 | J65: 0 | K65: 0 | Y65: =SUM(L65:X65) -> 0 | AA65: =Y65-Z65 -> 0
A66: 製造T | B66: ヤンマー | C66: PLM(Windchill）周辺システム開発 | D66: 新規 | E66: GMGが案件受注8000万。11月開始。要件定義参画→増額の可能性有 | F66: ー | G66: D | I66: 0 | J66: =600000+1500000*0.5 -> 1350000 | K66: =600000+1500000*0.5 -> 1350000 | Y66: =SUM(L66:X66) -> 0 | AA66: =Y66-Z66 -> 0
A67: 製造T | B67: Siemens | C67: NX/Teamcenter支援（バルミューダ） | D67: 新規 | E67: 7/8注文書受領→1,093,202円（ライセンス販売のみ）稼働中 | F67: ー | G67: A | I67: 0 | J67: 0 | K67: 0 | Y67: =SUM(L67:X67) -> 0 | AA67: =Y67-Z67 -> 0 | AF67: チーム合計 | AI67: Plan1.0比はInfluence込み
A68: 製造T | B68: アウトソーシング | C68: 人材派遣 提案支援 | D68: 新規 | E68: 6/27提案書提出 →ロスト（Sun Astrriskが受注） | F68: ー | G68: ー | Y68: =SUM(L68:X68) -> 0 | AA68: =Y68-Z68 -> 0 | AF68: Plan1.0比 | AG68: =AI78/AJ78 -> #REF! | AH68: 確度 | AI68: 下期 | AJ68: Plan1.0 | AK68: 100%KPI
A69: 製造T | B69: ダイキン | C69: グローバルデータ基盤構築 | D69: 継続 | E69: 2026年4月以降にインプリ提案。下期も案件ないかを相談する | F69: 臼井 | G69: ー | Y69: =SUM(L69:X69) -> 0 | AA69: =Y69-Z69 -> 0 | AF69: KPI比 | AG69: =AI78/AK78 -> #REF! | AH69: A | AI69: =AI6+AI30+AI55 -> #REF!
A70: 製造T | B70: ダイキン | C70: PLMコンサル | D70: 継続 | E70: 稼働中。10-11月受注済。別途PowerApps案件相談あり（年内対応） | F70: 臼井、BP | G70: A | I70: =1300000 -> 1300000 | J70: =1300000 -> 1300000 | K70: =3500000*0.1+3000000*0.15 -> 800000 | Y70: =SUM(L70:X70) -> 0 | AA70: =Y70-Z70 -> 0 | AH70: B | AI70: =AI7+AI31+AI56 -> 0
A71: 製造T | B71: DNP | C71: DNPのBPO業務 | D71: 新規 | E71: 提案先組織変更で再調整 | F71: 鷹野、川口、BP | G71: ー | Y71: =SUM(L71:X71) -> 0 | AA71: =Y71-Z71 -> 0 | AH71: C | AI71: =AI8+AI32+AI57 -> 0
A72: 製造T | B72: SCSK | C72: BPR案件、DXチームからの引継ぎ。 | D72: 継続 | E72: 稼働中 | F72: 臼井、松田 | G72: A | I72: 775000 | J72: 1250000 | K72: 1250000 | Y72: =SUM(L72:X72) -> 0 | AA72: =Y72-Z72 -> 0 | AH72: D | AI72: =AI9+AI33+AI58 -> 0
A73: 製造T | B73: ITEC阪急阪神 | C73: i-PLAT調査、導入支援 | D73: 新規 | E73: 2500万、コンサル1140万円、10月中旬開始予定→9/30失注 | F73: 鷹野、松田 | G73: ー | I73: 0 | J73: 0 | K73: 0 | Y73: =SUM(L73:X73) -> 0 | AA73: =Y73-Z73 -> 0 | AH73: O | AI73: =AI10+AI34+AI59 -> 0
A74: 製造T | B74: 実績積みあげ | Y74: =SUM(L74:X74) -> 0 | AH74: 積上げ | AI74: =SUM(AI69:AI73) -> #REF! | AJ74: 4.6683577e+08
A75: 製造T | B75: KMI | C75: KMI_コンカレントECM | D75: 新規 | E75: 稼働中。マレーシアの生産拠点DXをテーマに打合せ | F75: 臼井 | G75: A | I75: 600000 | J75: 600000 | K75: 600000 | Y75: =SUM(L75:X75) -> 0 | AA75: =Y75-Z75 -> 0
A76: 製造T | B76: ELECOM | C76: SSC PoC開発支援 | D76: 新規 | E76: 10/1提案→10/6内示。10/16プロジェクト開始予定（TCV995万円） | F76: 臼井 | G76: B | I76: =6650000/5 -> 1330000 | J76: =6650000/5*2 -> 2660000 | K76: =6650000/5*2 -> 2660000 | Y76: =SUM(L76:X76) -> 0 | AA76: =Y76-Z76 -> 0 | AH76: Influence
A77: 製造T | B77: SB C&S（ICT事業本部） | C77: SB C&S（ICT事業本部） | D77: 新規 | E77: 10/6提案書送付済（947～1280万円。松竹梅の見積提示） | G77: D
A78: 製造T | B78: SB C&S（田中ICO/情シス本部長） | C78: SB C&S（田中ICO/情シス本部長） | D78: 新規 | E78: 10/6週以降でRFPを受領予定。提案 | G78: D | AH78: 見込合計 | AI78: =AI74+AI76 -> #REF! | AJ78: =AJ74+AJ76 -> 4.6683577e+08 | AK78: 400000000
A79: 業務ITT | B79: デロイト協業（Akila） | C79: デロイト協業（Akila） | D79: 新規 | E79: 10/17：NDA締結中 | G79: O
A80: 業務改善T | B80: デロイト協業（基幹） | C80: デロイト協業（基幹） | D80: 新規 | E80: 10/17：NDA締結中 | G80: O
A81: 製造T | B81: オムロン | C81: オムロン | D81: 新規 | G81: O
A82: 製造T | B82: シマノ | C82: シマノ | D82: 新規 | E82: 役員への提案からなので案件化には時間がかかるFY26案件か | G82: O
A83: 製造T | B83: 竹中工務店関連1 | C83: AI戦略策定 | D83: 新規 | E83: 八巻さんTからの紹介 | G83: O
A84: 製造T | B84: 竹中工務店関連2 | C84: AI戦略策定 | D84: 新規 | E84: 八巻さんTからの紹介 | G84: O

Sheet Plan1.2まとめ
B2: 年間合計
A3: 行ラベル | B3: 合計 / 売上総額 | D3: 行ラベル | E3: 合計 / 売上総額 | F3: 合計 / 7月 | G3: 合計 / 8月 | H3: 合計 / 9月 | I3: 合計 / 10月 | J3: 合計 / 11月 | K3: 合計 / 12月 | L3: 下期合計
A4: 業務ITT | B4: 104238855 | D4: 業務ITT | E4: 104238855 | F4: 6372260 | G4: 7142260 | H4: 11332410 | I4: 12330300 | J4: 9440600 | K4: 9440750 | L4: =SUM(F4:K4) -> 56058580
A5: DAISUE CONSTRUCTION CO.,LTD. | B5: 600575 | D5: DAISUE CONSTRUCTION CO.,LTD. | E5: 600575 | F5: 0 | G5: 0 | H5: 150 | I5: 0 | J5: 0 | K5: 150
A6: JSOL Corporation | B6: 14685880 | D6: JSOL Corporation | E6: 14685880 | F6: 2261960 | G6: 1981960 | H6: 1701960 | I6: 1700000 | J6: 0 | K6: 0
A7: New Customer | B7: 2400 | D7: New Customer | E7: 2400 | F7: 300 | G7: 300 | H7: 300 | I7: 300 | J7: 600 | K7: 600
A8: NISHIMATSU CONSTRUCTION CO.,LTD. | B8: 7500000 | D8: NISHIMATSU CONSTRUCTION CO.,LTD. | E8: 7500000 | F8: 750000 | G8: 750000 | H8: 750000 | I8: 750000 | J8: 0 | K8: 0
A9: SHIMZ | B9: 6000000 | D9: SHIMZ | E9: 6000000 | F9: 1000000 | G9: 1000000 | H9: 1000000 | I9: 1000000 | J9: 1000000 | K9: 1000000
A10: Takenaka Corporation | B10: 75450000 | D10: Takenaka Corporation | E10: 75450000 | F10: 2360000 | G10: 3410000 | H10: 7880000 | I10: 8880000 | J10: 8440000 | K10: 8440000
A11: 業務改善T | B11: 211450000 | D11: 業務改善T | E11: 211450000 | F11: 20420000 | G11: 20420000 | H11: 21140000 | I11: 32240000 | J11: 30390000 | K11: 27890000 | L11: =SUM(F11:K11) -> 152500000
A12: Asunaro Aoki Construction Co.,Ltd. | B12: 77880000 | D12: Asunaro Aoki Construction Co.,Ltd. | E12: 77880000 | F12: 6350000 | G12: 6350000 | H12: 6350000 | I12: 6950000 | J12: 6950000 | K12: 6450000
A13: DAISUE CONSTRUCTION CO.,LTD. | B13: 100070000 | D13: DAISUE CONSTRUCTION CO.,LTD. | E13: 100070000 | F13: 14070000 | G13: 14070000 | H13: 14790000 | I13: 14790000 | J13: 12940000 | K13: 10940000
A14: アプリ展開①：鍜治田工務店（大末横展開） | B14: 13500000 | D14: アプリ展開①：鍜治田工務店（大末横展開） | E14: 13500000 | F14: 0 | G14: 0 | H14: 0 | I14: 4500000 | J14: 4500000 | K14: 4500000
A15: アプリ展開②：りんかい日産建設他（大末横展開） | B15: 9000000 | D15: アプリ展開②：りんかい日産建設他（大末横展開） | E15: 9000000 | F15: 0 | G15: 0 | H15: 0 | I15: 3000000 | J15: 3000000 | K15: 3000000
A16: アプリ展開③：錢高組他（大末横展開） | B16: 9000000 | D16: アプリ展開③：錢高組他（大末横展開） | E16: 9000000 | F16: 0 | G16: 0 | H16: 0 | I16: 3000000 | J16: 3000000 | K16: 3000000
A17: (空白) | B17: 2000000 | D17: (空白) | E17: 2000000
A18: 製造T | B18: 145797997 | D18: 製造T | E18: 145797997 | F18: 10837500 | G18: 20687500 | H18: 22687500 | I18: 23087500 | J18: 20687500 | K18: 20687500 | L18: =SUM(F18:K18) -> 118675000
A19: Daifuku Co., Ltd. | B19: 22637998 | D19: Daifuku Co., Ltd. | E19: 22637998 | F19: 3787500 | G19: 2237500 | H19: 2237500 | I19: 2637500 | J19: 2237500 | K19: 2237500 | L19: =SUM(F19:K19) -> 15375000
A20: DAIKIN INDUSTRIES, LTD. | B20: 8249950 | D20: DAIKIN INDUSTRIES, LTD. | E20: 8249950 | F20: 0 | G20: 0 | H20: 0 | I20: 0 | J20: 0 | K20: 0 | L20: =SUM(F20:K20) -> 0
A21: Daiwa House | B21: 20700000 | D21: Daiwa House | E21: 20700000 | F21: 3450000 | G21: 3450000 | H21: 3450000 | I21: 3450000 | J21: 3450000 | K21: 3450000 | L21: =SUM(F21:K21) -> 20700000
A22: DKI（ダイキン情報システム） | B22: 10000000 | D22: DKI（ダイキン情報システム） | E22: 10000000 | F22: 0 | G22: 2000000 | H22: 2000000 | I22: 2000000 | J22: 2000000 | K22: 2000000 | L22: =SUM(F22:K22) -> 10000000
A23: FAST RETAILING CO.,LTD. | B23: 0 | D23: FAST RETAILING CO.,LTD. | E23: 0 | F23: 0 | G23: 0 | H23: 0 | I23: 0 | J23: 0 | K23: 0 | L23: =SUM(F23:K23) -> 0
A24: IODATA | B24: 4000000 | D24: IODATA | E24: 4000000 | F24: 0 | G24: 0 | H24: 2000000 | I24: 2000000 | J24: 0 | K24: 0 | L24: =SUM(F24:K24) -> 4000000
A25: KONICA MINOLTA, INC. | B25: 3000000 | D25: KONICA MINOLTA, INC. | E25: 3000000 | F25: 0 | G25: 0 | H25: 0 | I25: 0 | J25: 0 | K25: 0 | L25: =SUM(F25:K25) -> 0
A26: LIXIL | B26: 20000000 | D26: LIXIL | E26: 20000000 | F26: 0 | G26: 4000000 | H26: 4000000 | I26: 4000000 | J26: 4000000 | K26: 4000000 | L26: =SUM(F26:K26) -> 20000000
A27: Mitsubishi UFJ Trust System | B27: 10000000 | D27: Mitsubishi UFJ Trust System | E27: 10000000 | F27: 0 | G27: 2000000 | H27: 2000000 | I27: 2000000 | J27: 2000000 | K27: 2000000 | L27: =SUM(F27:K27) -> 10000000
A28: Nissan Motor Co., Ltd. | B28: 0 | D28: Nissan Motor Co., Ltd. | E28: 0 | F28: 0 | G28: 0 | H28: 0 | I28: 0 | J28: 0 | K28: 0 | L28: =SUM(F28:K28) -> 0
A29: Panasonic Information Systems Co., Ltd. | B29: 0 | D29: Panasonic Information Systems Co., Ltd. | E29: 0 | F29: 0 | G29: 0 | H29: 0 | I29: 0 | J29: 0 | K29: 0 | L29: =SUM(F29:K29) -> 0
... A36: 野村不動産 | B36: 600000 | D36: 野村不動産 | E36: 600000 | F36: 600000 | G36: 0 | H36: 0 | I36: 0 | J36: 0 | K36: 0 | L36: =SUM(F36:K36) -> 600000
A37: (空白) | D37: (空白)
A38: (空白) | D38: (空白)
A39: 総計 | B39: 461486852 | D39: 総計 | E39: 461486852 | F39: 37629760 | G39: 48249760 | H39: 55159910 | I39: 67657800 | J39: 60518100 | K39: 58018250

Sheet Plan1.2
A1: サブチーム | B1: クライアント名 | C1: PJ名 | D1: 売上総額 | E1: 5－12月 | F1: 1月 | G1: 2月 | H1: 3月 | I1: 4月 | J1: 5月 | K1: 6月 | L1: 7月 | M1: 8月 | N1: 9月 | O1: 10月 | P1: 11月 | Q1: 12月 | R1: 確度：A,B,C
A2: 業務ITT | B2: DAISUE CONSTRUCTION CO.,LTD. | C2: BIMモデリング支援 | D2: =SUM(F2:Q2) -> 150000 | E2: =SUBTOTAL(9,J2:Q2) -> 0 | F2: 150000 | G2: 0 | H2: 0 | I2: 0 | J2: 0 | K2: 0 | L2: 0 | M2: 0 | N2: 0 | O2: 0 | P2: 0 | Q2: 0 | R2: A
A3: 業務ITT | B3: DAISUE CONSTRUCTION CO.,LTD. | C3: BIM動画フォーマット作成 | D3: =SUM(F3:Q3) -> 450000 | E3: =SUBTOTAL(9,J3:Q3) -> 0 | F3: 0 | G3: 0 | H3: 450000 | I3: 0 | J3: 0 | K3: 0 | L3: 0 | M3: 0 | N3: 0 | O3: 0 | P3: 0 | Q3: 0 | R3: A
A4: 業務ITT | B4: DAISUE CONSTRUCTION CO.,LTD. | C4: BIM動画作成 | D4: =SUM(F4:Q4) -> 575 | E4: =SUBTOTAL(9,J4:Q4) -> 575 | K4: 275 | N4: 150 | Q4: 150 | R4: A
A5: 業務ITT | B5: JSOL Corporation | C5: BIMテンプレート支援 | D5: =SUM(F5:Q5) -> 840000 | E5: =SUBTOTAL(9,J5:Q5) -> 0 | F5: 0 | G5: 0 | H5: 840000 | I5: 0 | J5: 0 | K5: 0 | L5: 0 | M5: 0 | N5: 0 | O5: 0 | P5: 0 | Q5: 0 | R5: A
A6: 業務ITT | B6: JSOL Corporation | C6: BIM汎用コンポーネント開発支援 | D6: =SUM(F6:Q6) -> 13840000 | E6: =SUBTOTAL(9,J6:Q6) -> 13840000 | F6: 0 | G6: 0 | H6: 0 | I6: 0 | J6: 3100000 | K6: 3100000 | L6: 2260000 | M6: 1980000 | N6: 1700000 | O6: 1700000 | P6: 0 | Q6: 0 | R6: A
A7: 業務ITT | B7: JSOL Corporation | C7: 建設DXコンサル支援（ナカノフドー建設） | D7: =SUM(F7:Q7) -> 5880 | E7: =SUBTOTAL(9,J7:Q7) -> 5880 | L7: 1960 | M7: 1960 | N7: 1960 | R7: B
A8: 業務ITT | B8: New Customer | C8: デジタルツイン（Akila PoCプラン） | D8: =SUM(F8:Q8) -> 2400 | E8: =SUBTOTAL(9,J8:Q8) -> 2400 | L8: 300 | M8: 300 | N8: 300 | O8: 300 | P8: 600 | Q8: 600 | R8: O
A9: 業務ITT | B9: NISHIMATSU CONSTRUCTION CO.,LTD. | C9: BIMモデリング支援 | D9: =SUM(F9:Q9) -> 7500000 | E9: =SUBTOTAL(9,J9:Q9) -> 4500000 | F9: 750000 | G9: 750000 | H9: 750000 | I9: 750000 | J9: 750000 | K9: 750000 | L9: 750000 | M9: 750000 | N9: 750000 | O9: 750000 | P9: 0 | Q9: 0 | R9: O
A10: 業務ITT | B10: SHIMZ | C10: FM事業支援 | D10: =SUM(F10:Q10) -> 6000000 | E10: =SUBTOTAL(9,J10:Q10) -> 6000000 | F10: 0 | G10: 0 | H10: 0 | I10: 0 | J10: 0 | K10: 0 | L10: 1000000 | M10: 1000000 | N10: 1000000 | O10: 1000000 | P10: 1000000 | Q10: 1000000 | R10: B
A11: 業務ITT | B11: Takenaka Corporation | C11: BIM基盤構築（1-2月）※コンサル | D11: =SUM(F11:Q11) -> 11550000 | E11: =SUBTOTAL(9,J11:Q11) -> 0 | F11: 6600000 | G11: 4950000 | H11: 0 | I11: 0 | J11: 0 | K11: 0 | L11: 0 | M11: 0 | N11: 0 | O11: 0 | P11: 0 | Q11: 0 | R11: A
A12: 業務ITT | B12: Takenaka Corporation | C12: BIM基盤構築（3-7月）※コンサル | D12: =SUM(F12:Q12) -> 25100000 | E12: =SUBTOTAL(9,J12:Q12) -> 12120000 | F12: 0 | G12: 0 | H12: 6700000 | I12: 6280000 | J12: 5580000 | K12: 4180000 | L12: 2360000 | M12: 0 | N12: 0 | O12: 0 | P12: 0 | Q12: 0 | R12: A
A13: 業務ITT | B13: Takenaka Corporation | C13: BIM基盤構築（8-12月）※コンサル | D13: =SUM(F13:Q13) -> 20050000 | E13: =SUBTOTAL(9,J13:Q13) -> 20050000 | F13: 0 | G13: 0 | H13: 0 | I13: 0 | J13: 0 | K13: 0 | L13: 0 | M13: 3410000 | N13: 3880000 | O13: 3880000 | P13: 4440000 | Q13: 4440000 | R13: B
A14: 業務ITT | B14: Takenaka Corporation | C14: BIM基盤構築（システム要件定義） | D14: =SUM(F14:Q14) -> 1750000 | E14: =SUBTOTAL(9,J14:Q14) -> 0 | F14: 1750000 | G14: 0 | H14: 0 | I14: 0 | J14: 0 | K14: 0 | L14: 0 | M14: 0 | N14: 0 | O14: 0 | P14: 0 | Q14: 0 | R14: A
A15: 業務ITT | B15: Takenaka Corporation | C15: 大阪本店 Akila導入検証 | D15: =SUM(F15:Q15) -> 3000000 | E15: =SUBTOTAL(9,J15:Q15) -> 3000000 | F15: 0 | G15: 0 | H15: 0 | I15: 0 | J15: 0 | K15: 0 | L15: 0 | M15: 0 | N15: 0 | O15: 1000000 | P15: 1000000 | Q15: 1000000 | R15: O
A16: 業務ITT | B16: Takenaka Corporation | C16: 中央監視システム開発支援 | D16: =SUM(F16:Q16) -> 2000000 | E16: =SUBTOTAL(9,J16:Q16) -> 2000000 | F16: 0 | G16: 0 | H16: 0 | I16: 0 | J16: 0 | K16: 0 | L16: 0 | M16: 0 | N16: 1000000 | O16: 1000000 | P16: 0 | Q16: 0 | R16: C
A17: 業務ITT | B17: Takenaka Corporation | C17: BIM基盤構築（開発） | D17: =SUM(F17:Q17) -> 12000000 | E17: =SUBTOTAL(9,J17:Q17) -> 12000000 | N17: 3000000 | O17: 3000000 | P17: 3000000 | Q17: 3000000 | R17: O
A18: 業務改善T | B18: Asunaro Aoki Construction Co.,Ltd. | C18: AAK_スマートBPO業務・方針整理（1月～9月） | D18: =SUM(F18:Q18) -> 22730000 | F18: 4900000 | G18: 2900000 | H18: 2330000 | I18: 2100000 | J18: 2100000 | K18: 2100000 | L18: 2100000 | M18: 2100000 | N18: 2100000 | O18: 0 | P18: 0 | Q18: 0 | R18: A
A19: 業務改善T | B19: Asunaro Aoki Construction Co.,Ltd. | C19: AAK_スマートBPO業務・方針整理（10月～12月） | D19: =SUM(F19:Q19) -> 6300000 | F19: 0 | G19: 0 | H19: 0 | I19: 0 | J19: 0 | K19: 0 | L19: 0 | M19: 0 | N19: 0 | O19: 2100000 | P19: 2100000 | Q19: 2100000 | R19: A
A20: 業務改善T | B20: Asunaro Aoki Construction Co.,Ltd. | C20: 業務改善（1月～9月） | D20: =SUM(F20:Q20) -> 34800000 | F20: 4600000 | G20: 4600000 | H20: 4600000 | I20: 2750000 | J20: 2750000 | K20: 2750000 | L20: 4250000 | M20: 4250000 | N20: 4250000 | O20: 0 | P20: 0 | Q20: 0 | R20: A
A21: 業務改善T | B21: Asunaro Aoki Construction Co.,Ltd. | C21: 業務改善（10月～12月） | D21: =SUM(F21:Q21) -> 14050000 | F21: 0 | G21: 0 | H21: 0 | I21: 0 | J21: 0 | K21: 0 | L21: 0 | M21: 0 | N21: 0 | O21: 4850000 | P21: 4850000 | Q21: 4350000 | R21: A
A22: 業務改善T | B22: DAISUE CONSTRUCTION CO.,LTD. | C22: [Renew] DX system AMS phase（1月～9月） | D22: =SUM(F22:Q22) -> 8400000 | E22: =SUBTOTAL(9,J22:Q22) -> 3750000 | F22: 1300000 | G22: 1300000 | H22: 1300000 | I22: 750000 | J22: 750000 | K22: 750000 | L22: 750000 | M22: 750000 | N22: 750000 | O22: 0 | P22: 0 | Q22: 0 | R22: A
A23: 業務改善T | B23: DAISUE CONSTRUCTION CO.,LTD. | C23: [Renew] DX system AMS phase（10月～12月） | D23: =SUM(F23:Q23) -> 2250000 | E23: =SUBTOTAL(9,J23:Q23) -> 2250000 | F23: 0 | G23: 0 | H23: 0 | I23: 0 | J23: 0 | K23: 0 | L23: 0 | M23: 0 | N23: 0 | O23: 750000 | P23: 750000 | Q23: 750000 | R23: A
A24: 業務改善T | B24: DAISUE CONSTRUCTION CO.,LTD. | C24: DXS-2 | D24: =SUM(F24:Q24) -> 12300000 | E24: =SUBTOTAL(9,J24:Q24) -> 12300000 | F24: 0 | G24: 0 | H24: 0 | I24: 0 | J24: 0 | K24: 0 | L24: 1000000 | M24: 1000000 | N24: 3500000 | O24: 3500000 | P24: 1650000 | Q24: 1650000 | R24: O
A25: 業務改善T | B25: DAISUE CONSTRUCTION CO.,LTD. | C25: 基幹システムリプレイス（1月～9月） | D25: =SUM(F25:Q25) -> 47500000 | E25: =SUBTOTAL(9,J25:Q25) -> 47500000 | F25: 0 | G25: 0 | H25: 0 | I25: 0 | J25: 0 | K25: 12320000 | L25: 12320000 | M25: 12320000 | N25: 10540000 | O25: 0 | P25: 0 | Q25: 0 | R25: A
A26: 業務改善T | B26: DAISUE CONSTRUCTION CO.,LTD. | C26: 基幹システムリプレイス（10月～12月） | D26: =SUM(F26:Q26) -> 29620000 | E26: =SUBTOTAL(9,J26:Q26) -> 29620000 | F26: 0 | G26: 0 | H26: 0 | I26: 0 | J26: 0 | K26: 0 | L26: 0 | M26: 0 | N26: 0 | O26: 10540000 | P26: 10540000 | Q26: 8540000 | R26: A
A27: 業務改善T | B27: アプリ展開①：鍜治田工務店（大末横展開） | C27: DXS展開 | D27: =SUM(F27:Q27) -> 13500000 | E27: =SUBTOTAL(9,J27:Q27) -> 13500000 | F27: 0 | G27: 0 | H27: 0 | I27: 0 | J27: 0 | K27: 0 | L27: 0 | M27: 0 | N27: 0 | O27: 4500000 | P27: 4500000 | Q27: 4500000 | R27: O
A28: 業務改善T | B28: アプリ展開②：りんかい日産建設他（大末横展開） | C28: DXS展開 | D28: =SUM(F28:Q28) -> 9000000 | E28: =SUBTOTAL(9,J28:Q28) -> 9000000 | F28: 0 | G28: 0 | H28: 0 | I28: 0 | J28: 0 | K28: 0 | L28: 0 | M28: 0 | N28: 0 | O28: 3000000 | P28: 3000000 | Q28: 3000000 | R28: O
A29: 業務改善T | B29: アプリ展開③：錢高組他（大末横展開） | C29: DXS展開 | D29: =SUM(F29:Q29) -> 9000000 | E29: =SUBTOTAL(9,J29:Q29) -> 9000000 | F29: 0 | G29: 0 | H29: 0 | I29: 0 | J29: 0 | K29: 0 | L29: 0 | M29: 0 | N29: 0 | O29: 3000000 | P29: 3000000 | Q29: 3000000 | R29: O
A30: 製造T | B30: Daifuku Co., Ltd. | C30: 3D CADチェックツール開発(第二弾) | D30: =SUM(F30:Q30) -> 1673347.5 | E30: =SUBTOTAL(9,J30:Q30) -> 800000 | F30: 439050 | G30: 0 | H30: 0 | I30: 434297.5 | J30: 0 | K30: 0 | L30: 400000 | M30: 0 | N30: 0 | O30: 400000 | P30: 0 | Q30: 0 | R30: A
A31: 製造T | B31: Daifuku Co., Ltd. | C31: 3Dモデリング2025年分作業 (BPO) | D31: =SUM(F31:Q31) -> 382950 | F31: =30900+16650 -> 47550 | G31: 129900 | H31: 70950 | I31: 134550 | J31: 0 | K31: 0 | L31: 0 | M31: 0 | N31: 0 | O31: 0 | P31: 0 | Q31: 0 | R31: A
A32: 製造T | B32: Daifuku Co., Ltd. | C32: AIものづくり支援環境構築 | D32: =SUM(F32:Q32) -> 20503700 | E32: =SUBTOTAL(9,J32:Q32) -> 18893750 | F32: 0 | G32: 462450 | H32: 1147500 | I32: 0 | J32: 181250 | K32: 4137500 | L32: 3387500 | M32: 2237500 | N32: 2237500 | O32: 2237500 | P32: 2237500 | Q32: 2237500 | R32: A
A33: 製造T | B33: Daifuku Co., Ltd. | C33: 3D 格納状態図作成ツール開発 | D33: =SUM(F33:Q33) -> 78000 | E33: =SUBTOTAL(9,J33:Q33) -> 0 | F33: 78000 | R33: A
A34: 製造T | B34: DAIKIN INDUSTRIES, LTD. | C34: AI×CADによる設計自動化に向けたロードマップ作成支援 | D34: =SUM(F34:Q34) -> 2599950 | E34: =SUBTOTAL(9,J34:Q34) -> 0 | F34: 0 | G34: 858000 | H34: 1741950 | I34: 0 | J34: 0 | K34: 0 | L34: 0 | M34: 0 | N34: 0 | O34: 0 | P34: 0 | Q34: 0 | R34: A
A35: 製造T | B35: DAIKIN INDUSTRIES, LTD. | C35: ITインフラ基盤調査報告書作成支援 | D35: =SUM(F35:Q35) -> 5050000 | E35: =SUBTOTAL(9,J35:Q35) -> 3787560 | F35: 0 | G35: 0 | H35: 0 | I35: 1262440 | J35: =2525000-I35 -> 1262560 | K35: 2525000 | L35: 0 | M35: 0 | N35: 0 | O35: 0 | P35: 0 | Q35: 0 | R35: A
A36: 製造T | B36: DAIKIN INDUSTRIES, LTD. | C36: NX addon development 2025 | D36: =SUM(F36:Q36) -> 600000 | E36: =SUBTOTAL(9,J36:Q36) -> 0 | F36: 300000 | G36: 300000 | H36: 0 | I36: 0 | J36: 0 | K36: 0 | L36: 0 | M36: 0 | N36: 0 | O36: 0 | P36: 0 | Q36: 0 | R36: A
A37: 製造T | B37: Daiwa House | C37: 大和ハウス AI支援 | D37: =SUM(F37:Q37) -> 20700000 | E37: =SUBTOTAL(9,J37:Q37) -> 20700000 | F37: 0 | G37: 0 | H37: 0 | I37: 0 | J37: 0 | K37: 0 | L37: 3450000 | M37: 3450000 | N37: 3450000 | O37: 3450000 | P37: 3450000 | Q37: 3450000 | R37: O
A38: 製造T | B38: DKI（ダイキン情報システム） | C38: akaBot支援 | D38: =SUM(F38:Q38) -> 10000000 | E38: =SUBTOTAL(9,J38:Q38) -> 10000000 | F38: 0 | G38: 0 | H38: 0 | I38: 0 | J38: 0 | K38: 0 | L38: 0 | M38: 2000000 | N38: 2000000 | O38: 2000000 | P38: 2000000 | Q38: 2000000 | R38: O
A39: 製造T | B39: FAST RETAILING CO.,LTD. | C39: FR UiPath支援 | D39: =SUM(F39:Q39) -> 0 | E39: =SUBTOTAL(9,J39:Q39) -> 0 | F39: 0 | G39: 0 | H39: 0 | I39: 0 | J39: 0 | K39: 0 | L39: 0 | M39: 0 | N39: 0 | O39: 0 | P39: 0 | Q39: 0 | R39: O
A40: 製造T | B40: IODATA | C40: PM/PL要員育成ロードマップ作成、教育支援 | D40: =SUM(F40:Q40) -> 4000000 | E40: =SUBTOTAL(9,J40:Q40) -> 4000000 | F40: 0 | G40: 0 | H40: 0 | I40: 0 | J40: 0 | K40: 0 | L40: 0 | M40: 0 | N40: 2000000 | O40: 2000000 | P40: 0 | Q40: 0 | R40: C
A41: 製造T | B41: KONICA MINOLTA, INC. | C41: ECM/CDM replacement assessment phase | D41: =SUM(F41:Q41) -> 3000000 | E41: =SUBTOTAL(9,J41:Q41) -> 0 | F41: 900000 | G41: 900000 | H41: 1200000 | I41: 0 | J41: 0 | K41: 0 | L41: 0 | M41: 0 | N41: 0 | O41: 0 | P41: 0 | Q41: 0 | R41: A
A42: 製造T | B42: KONICA MINOLTA, INC. | C42: KMI_CDM刷新アセスメントフェーズ | D42: =SUM(F42:Q42) -> 0 | E42: =SUBTOTAL(9,J42:Q42) -> 0 | F42: 0 | G42: 0 | H42: 0 | I42: 0 | J42: 0 | K42: 0 | L42: 0 | M42: 0 | N42: 0 | O42: 0 | P42: 0 | Q42: 0 | R42: O
A43: 製造T | B43: LIXIL | C43: BPO業務自動化支援 | D43: =SUM(F43:Q43) -> 20000000 | E43: =SUBTOTAL(9,J43:Q43) -> 20000000 | F43: 0 | G43: 0 | H43: 0 | I43: 0 | J43: 0 | K43: 0 | L43: 0 | M43: 4000000 | N43: 4000000 | O43: 4000000 | P43: 4000000 | Q43: 4000000 | R43: O
A44: 製造T | B44: Mitsubishi UFJ Trust System | C44: akaBot検証（4-6月） | D44: =SUM(F44:Q44) -> 0 | E44: =SUBTOTAL(9,J44:Q44) -> 0 | F44: 0 | G44: 0 | H44: 0 | I44: 0 | J44: 0 | K44: 0 | L44: 0 | M44: 0 | N44: 0 | O44: 0 | P44: 0 | Q44: 0 | R44: O
A45: 製造T | B45: Mitsubishi UFJ Trust System | C45: UiPath開発 | D45: =SUM(F45:Q45) -> 10000000 | E45: =SUBTOTAL(9,J45:Q45) -> 10000000 | F45: 0 | G45: 0 | H45: 0 | I45: 0 | J45: 0 | K45: 0 | L45: 0 | M45: 2000000 | N45: 2000000 | O45: 2000000 | P45: 2000000 | Q45: 2000000 | R45: C
A46: 製造T | B46: Nissan Motor Co., Ltd. | C46: 仮）日産自動車 TCNX支援 | D46: =SUM(F46:Q46) -> 0 | E46: =SUBTOTAL(9,J46:Q46) -> 0 | F46: 0 | G46: 0 | H46: 0 | I46: 0 | J46: 0 | K46: 0 | L46: 0 | M46: 0 | N46: 0 | O46: 0 | P46: 0 | Q46: 0 | R46: O
A47: 製造T | B47: Panasonic Information Systems Co., Ltd. | C47: PISC_CADPLMサポート | D47: =SUM(F47:Q47) -> 0 | E47: =SUBTOTAL(9,J47:Q47) -> 0 | F47: 0 | G47: 0 | H47: 0 | I47: 0 | J47: 0 | K47: 0 | L47: 0 | M47: 0 | N47: 0 | O47: 0 | P47: 0 | Q47: 0 | R47: O
... A56: 製造T | B56: 野村不動産 | C56: 営業支援ツール | D56: =SUM(F56:Q56) -> 600000 | E56: =SUBTOTAL(9,J56:Q56) -> 600000 | F56: 0 | G56: 0 | H56: 0 | I56: 0 | J56: 0 | K56: 0 | L56: 600000 | M56: 0 | N56: 0 | O56: 0 | P56: 0 | Q56: 0 | R56: B
A57: 業務改善T | C57: 青木あすなろの出張調整分・請求後相殺 | D57: =SUM(F57:Q57) -> 2000000 | K57: 2000000 | R57: A

Sheet 250903
B2: Plan1.2比 | C2: ■竹中＋BIMで、計画通り推移
B3: 1.6766451 | C3: 確度 | D3: 下期 | E3: Plan1.2 | G3: 合計 | H3: Plan1.2
C4: A | D4: 33430000
C5: B | D5: 58160000
C6: C | D6: 0
C7: D | D7: 900000
C8: O | D8: 1500000
C9: 合計 | D9: 93990000 | E9: 56058375
B12: Plan1.2比 | C12: ■大末＋青木で計画通りに、TCGの基幹：1億案件、提案中確度高め
B13: 0.85947541 | C13: 確度 | D13: 下期 | E13: Plan1.2
C14: A | D14: 68710000
C15: B | D15: 0
C16: C | D16: 52220000
C17: D | D17: 7820000
C18: O | D18: 2320000
C20: 合計 | D20: 131070000 | E20: 152500000
B23: Plan1.2比 | C23: ■ダイフク、YKK、ダイワ等、コネクションがある案件が軒並み縮小、新規BPOを中心に積み上げ中
B24: 0.56513905 | C24: 確度 | D24: 下期 | E24: Plan1.2
C25: A | D25: 38638301
C26: B | D26: 14475000
C27: D | D27: 25875000
C28: O | D28: 0
C29: 合計 | D29: 78988301 | E29: 132690000
B32: Plan1.2比 | C32: 確度 | D32: 下期 | E32: Plan1.2
B33: =D37/E37 -> 0.87979408 | C33: A | D33: =D4+D14+D25 -> 140778301 | E33: =E4+E14+E25 -> 0
B34: =D37-E37 -> -41020074 | C34: B | D34: =D5+D15+D26 -> 72635000 | E34: =E5+E15+E26 -> 0
C35: D | D35: =D6+D16 -> 52220000 | E35: =E6+E16 -> 0
C36: O | D36: =D7+D17+D27 -> 34595000 | E36: =E7+E17+E27 -> 0
C37: 合計 | D37: =SUM(D33:D36) -> 300228301 | E37: =E9+E20+E29 -> 341248375 | H37: 461486852

Sheet チーム別PreSales
A2: 9月まで
A3: 行ラベル | B3: 合計 / FCJ 5%
A4: AAK | B4: 138000 | D4: 業務IT | E4: =GETPIVOTDATA("FCJ 5%",$A$3,"Account","JSOL")+GETPIVOTDATA("FCJ 5%",$A$3,"Account","TNK") -> 30956700
A5: DAIKIN | B5: 771396 | D5: 業務改善 | E5: =GETPIVOTDATA("FCJ 5%",$A$3,"Account","AAK")+GETPIVOTDATA("FCJ 5%",$A$3,"Account","DAISUE") -> 734028.75
A6: DAISUE | B6: 596028.75 | D6: 製造PKG | E6: =GETPIVOTDATA("FCJ 5%",$A$3,"Account","DAIKIN")+GETPIVOTDATA("FCJ 5%",$A$3,"Account","DFK")+GETPIVOTDATA("FCJ 5%",$A$3,"Account","YKKAP") -> 2759811.4
A7: DFK | B7: 1938915.4 | E7: =SUM(E4:E6) -> 34450540
A8: JSOL | B8: 771500
A9: NM | B9: 0
A10: OrixB | B10: 0
A11: TNK | B11: 30185200
A12: YKKAP | B12: 49500
A13: 総計 | B13: 34450540

Sheet PreSales
A1: Project Name | B1: CRM Quote | C1: Opp ID | D1: Account | E1: Opp presale-team | F1: Dept | G1: FCJ Members | H1: Updated | I1: Period | J1: Total Proposed Revenue(FPT+FCJ) | K1: Period | L1: Total estimated revenue (FPT+FCJ) | M1: Period | N1: Total Contracted Revenue(TCV: FPT+FCJ) | O1: FCJ 5%
A2: TCNX技術者（フィ）_20250921-20251220 | B2: DAIKIN/FJP/250918/001 | C2: OPP-102924-6-FJP-DAIKIN | D2: DAIKIN | E2: FJP.FA.PDS | F2: BX GCS | G2: Usui.Masahiro | I2: 0 | J2: 2400000 | K2: 60 | L2: 2400000 | M2: 0 | N2: 2400000 | O2: 120000
A3: TCNX技術者（クォン）_20250921-20251220 | B3: DAIKIN/FJP/250922/001 | C3: OPP-102924-6-FJP-DAIKIN | D3: DAIKIN | E3: FJP.FA.PDS | F3: BX GCS | G3: Usui.Masahiro | I3: 0 | J3: 2280000 | K3: #REF! | L3: 2280000 | M3: 67191000 | N3: 2280000 | O3: 114000
A4: NX,TC業務支援Q3_Dan-202510-202512 | B4: DAIKIN/FJP/250925/001 | C4: OPP-102924-6-FJP-DAIKIN | D4: DAIKIN | E4: FJP.FA.PDS | F4: BX GCS | G4: Usui.Masahiro | I4: 0 | J4: 2400000 | K4: 60 | L4: 2400000 | M4: 0 | N4: 2400000 | O4: 120000
A5: BIM活用基盤整備構想策定の業務支援（08月～12月）_202508-202512 | B5: TNK/FJP/250905/001 | C5: OPP-082825-1-FJP-TNK | D5: TNK | E5: FJP.GMG.MCW | F5: BX GCS | G5: Tetsuya Yamaki | I5: 0 | J5: 39440000 | K5: #REF! | L5: 39440000 | M5: #REF! | N5: 3120000 | O5: 156000
A6: BIM活用基盤_STEP1開発_20250829-20261231_FJP.GMG-FHM.JPG-Buffer | B6: TNK/FJP/250905/002 | C6: OPP-082825-1-FJP-TNK | D6: TNK | E6: FJP.GMG.MCW | F6: BX GCS | G6: Tetsuya Yamaki | I6: 0 | J6: 180299000 | K6: 5258920 | L6: 180299000 | M6: 89149920 | N6: 180299000 | O6: 9014950
A7: BIM活用基盤_STEP1開発_20250815-20261231_Comtor G0 | B7: TNK/FJP/250926/002 | C7: OPP-082825-1-FJP-TNK | D7: TNK | E7: FJP.GMG.MCW | F7: BX GCS | G7: Tetsuya Yamaki | I7: 0 | J7: 574000 | K7: #REF! | L7: 574000 | M7: 269448920 | N7: 574000 | O7: 28700
A8: BIM活用基盤_STEP1開発_20250815-20261231_F1.CSM | B8: TNK/FJP/250929/001 | C8: OPP-082825-1-FJP-TNK | D8: TNK | E8: FJP.GMG.MCW | F8: BX GCS | G8: Tetsuya Yamaki | I8: 0 | J8: 6392000 | K8: 60 | L8: 6392000 | M8: 0 | N8: 6392000 | O8: 319600
A9: DLM基盤_STEP1開発_202509-202612 | B9: TNK/FJP/250930/001 | C9: OPP-060425-1-FJP-TNK | D9: TNK | E9: FJP.GMG.MCW | F9: BX GCS | G9: Tetsuya Yamaki | I9: 0 | J9: 476154000 | K9: #REF! | L9: 476154000 | M9: 209223920 | N9: 412479000 | O9: 20623950
A10: DLM基盤_STEP1開発_202509-202512_Comtor G0 | B10: TNK/FJP/251001/001 | C10: OPP-060425-1-FJP-TNK | D10: TNK | E10: FJP.GMG.MCW | F10: BX GCS | G10: Tetsuya Yamaki | I10: 0 | J10: 840000 | K10: #REF! | L10: 840000 | M10: #REF! | N10: 840000 | O10: 42000
A11: BIM活用基盤_STEP1開発_20250815-20261231_FCJ | B11: TNK/FJP/250929/002 | C11: OPP-082825-1-FJP-TNK | D11: TNK | E11: FJP.GMG.MCW | F11: BX GCS | G11: Tetsuya Yamaki | I11: 0 | J11: 24000000 | K11: 60 | L11: 24000000 | M11: 0 | N11: 0 | O11: 0
A12: 要件定義業務支援 (中村)_FCJ_Nakamura. Takuo (takuon)_20251021-20260331 | B12: NM/FJP/250930/001 | C12: OPP-010924-1-FJP-NM | D12: NM | E12: FCJ.BX.GCS | F12: BX GCS | G12: takuon | I12: 0 | J12: 3984375 | K12: 60 | L12: 3984375 | M12: 0 | N12: 0 | O12: 0
A13: JSOL -SAP- JD NET Jun-August _20250520-2050831 | B13: JSOL/FJP/250527/001 | C13: OPP-041625-1-FJP-JSOL | D13: JSOL | E13: FCJ.BX.GCS | F13: BX GCS | I13: 0 | J13: 11730000 | K13: #REF! | L13: 11730000 | M13: #REF! | N13: 11730000 | O13: 586500
A14: RPA 運用・検証支援_2025/7/15-2025/9/30 | B14: OrixB/FJP/250911/001 | C14: OPP-102924-1-FJP-OrixB | D14: OrixB | E14: FCJ.BX.GCS | F14: BX GCS | I14: 0 | J14: 5000000 | K14: #REF! | L14: 5000000 | M14: 11730000 | N14: 0 | O14: 0
A15: ﾊﾟﾚｯﾄｺﾝﾍﾞﾔｾｲｻﾝｾｲｶｲﾊﾂ モデル作成_20240827発注分_20250827-20250905 | B15: DFK/FJP/250918/001 | C15: OPP-120324-2-FJP-DFK | D15: DFK | E15: FCJ.BX.GCS | F15: BX GCS | I15: 0 | J15: 51394 | K15: 3000000 | L15: 51394 | M15: 24322500 | N15: 51394 | O15: 2569.7
A16: 【特急対応】3Dモデリング54_2025/8/28～2025/9/1 | B16: DFK/FJP/250925/001 | C16: OPP-120324-1-FJP-DFK | D16: DFK | E16: FCJ.BX.GCS | F16: BX GCS | I16: 0 | J16: 176690 | K16: #REF! | L16: 176690 | M16: 18431394 | N16: 176690 | O16: 8834.5
A17: AI活用拡大(Q3)＿FPTクラウド費用(2025年8月分) | B17: DFK/FJP/250929/001 | C17: OPP-030725-1-FJP-DFK | D17: DFK | E17: FCJ.BX.GCS | F17: BX GCS | I17: 0 | J17: 32154 | K17: #REF! | L17: 32154 | M17: 283033984 | N17: 32154 | O17: 1607.7
A18: ﾊﾟﾚｯﾄｺﾝﾍﾞﾔｾｲｻﾝｾｲｶｲﾊﾂ モデル作成_K3136137_20250904-20250926 | B18: DFK/FJP/250912/001 | C18: OPP-120324-2-FJP-DFK | D18: DFK | E18: FCJ.BX.GCS | F18: BX GCS | I18: 0 | J18: 505188 | K18: #REF! | L18: 505188 | M18: 17640238 | N18: 505188 | O18: 25259.4
A19: ﾊﾟﾚｯﾄｺﾝﾍﾞﾔｾｲｻﾝｾｲｶｲﾊﾂ モデル作成_K3136138_20240904-20250926 | B19: DFK/FJP/250925/004 | C19: OPP-120324-2-FJP-DFK | D19: DFK | E19: FCJ.BX.GCS | F19: BX GCS | I19: 0 | J19: 674688 | K19: #REF! | L19: 674688 | M19: #REF! | N19: 674688 | O19: 33734.4
A20: 【特急対応】3Dモデリング55_2025/9/8～2025/9/9 | B20: DFK/FJP/250925/003 | C20: OPP-120324-1-FJP-DFK | D20: DFK | E20: FCJ.BX.GCS | F20: BX GCS | I20: 0 | J20: 233451 | K20: 10500000 | L20: 233451 | M20: 31297614 | N20: 233451 | O20: 11672.55
A21: BTPの開発支援_202509-10 | B21: JSOL/FJP/250912/001 | C21: OPP-041625-1-FJP-JSOL | D21: JSOL | E21: FCJ.BX.GCS | F21: BX GCS | I21: 0 | J21: 3668000 | K21: 233451 | L21: 3668000 | M21: 109087805 | N21: 3668000 | O21: 183400
A22: BTPの開発支援_202509-10_Comtor G0 | B22: JSOL/FJP/250912/002 | C22: OPP-041625-1-FJP-JSOL | D22: JSOL | E22: FCJ.BX.GCS | F22: BX GCS | I22: 0 | J22: 32000 | K22: #REF! | L22: 32000 | M22: 5113481 | N22: 32000 | O22: 1600
A23: 【特急対応】3Dモデリング56_2025/9/11～2025/9/18 | B23: DFK/FJP/250925/005 | C23: OPP-120324-1-FJP-DFK | D23: DFK | E23: FCJ.BX.GCS | F23: BX GCS | I23: 0 | J23: 241856 | K23: #REF! | L23: 241856 | M23: 320473325 | N23: 241856 | O23: 12092.8
A24: 設計アウトプットの改革 IDW作成_20250918発注分_20250918-20251020 | B24: DFK/FJP/250924/001 | C24: OPP-120324-2-FJP-DFK | D24: DFK | E24: FCJ.BX.GCS | F24: BX GCS | I24: 0 | J24: 994984 | K24: 60 | L24: 994984 | M24: 0 | N24: 994984 | O24: 49749.2
A25: 【特急対応】3Dモデリング57_2025/9/19～2025/10/1 | B25: DFK/FJP/250925/002 | C25: OPP-120324-1-FJP-DFK | D25: DFK | E25: FCJ.BX.GCS | F25: BX GCS | I25: 0 | J25: 401021 | K25: #REF! | L25: 401021 | M25: 994984 | N25: 401021 | O25: 20051.05
A26: AAK_業務改善・デジタル化の案件【B】、【C】フェーズ_2025年10月11月12月 | B26: AAK/FJP/251001/001 | C26: OPP-031125-3-FJP-AAK | D26: AAK | E26: FCJ.BX.GCS | F26: BX GCS | I26: 0 | J26: 6000000 | K26: #REF! | L26: 6000000 | M26: 1396005 | N26: 0 | O26: 0
A27: 汎用コンポーネント(マンション試行用)開発支援_交通費_202508 | B27: JSOL/FJP/250925/001 | C27: OPP-031225-1-FJP-JSOL | D27: JSOL | E27: FCJ.BX.GCS | F27: BX GCS | I27: 0 | J27: 28380 | K27: #REF! | L27: 28380 | M27: 401021 | N27: 0 | O27: 0
A28: 建設DXコンサルのビジネス検討・推進支援_202510-202603 | B28: JSOL/FJP/251001/001 | C28: OPP-090825-1-FJP-JSOL | D28: JSOL | E28: FCJ.BX.GCS | F28: BX GCS | I28: 0 | J28: 4800000 | K28: 48000000 | L28: 4800000 | M28: 0 | N28: 0 | O28: 0
A29: N社向けIT企画構想支援_202510-202603 | B29: JSOL/FJP/251002/002 | C29: OPP-090925-1-FJP-JSOL | D29: JSOL | E29: FCJ.BX.GCS | F29: BX GCS | I29: 0 | J29: 3360000 | K29: #REF! | L29: 3360000 | M29: 0 | N29: 0 | O29: 0
A30: N社向けPJ推進のご支援_202510-202603 | B30: JSOL/FJP/251002/001 | C30: OPP-090925-1-FJP-JSOL | D30: JSOL | E30: FCJ.BX.GCS | F30: BX GCS | I30: 0 | J30: 8400000 | K30: #REF! | L30: 8400000 | M30: 1396005 | N30: 0 | O30: 0
A31: 汎用コンポーネント(マンション試行用)開発支援_交通費_202509 | B31: JSOL/FJP/251002/003 | C31: OPP-031225-1-FJP-JSOL | D31: JSOL | E31: FCJ.BX.GCS | F31: BX GCS | I31: 0 | J31: 51181 | K31: #REF! | L31: 51181 | M31: 0 | N31: 0 | O31: 0
A32: 大正区鶴町冷凍冷蔵物流計画設備電気インフラモデル製作業務_20250113-20250120 | B32: DAISUE/FJP/250116/001 | C32: OPP-010924-1-FJP-DAISUE | D32: DAISUE | E32: FJP.GMG.MCW | F32: BX GCS | G32: kato.fumie | I32: 0 | J32: 248250 | K32: 24440000 | L32: 248250 | M32: 251186293 | N32: 248250 | O32: 12412.5
A33: YKKAP_次期AP CADシステム刷新プロジェクト_2024/12/16-2025/3/31 | B33: YKKAP/FJP/250109/001 | C33: OPP-092724-1-FJP-YKKAP | D33: YKKAP | E33: FCJ.BX.GCS | F33: BX GCS | I33: 0 | J33: 9600000 | K33: #REF! | L33: 9600000 | M33: 8515480 | N33: 990000 | O33: 49500
A34: 【特急対応】3Dモデリング28_20250120依頼分_20250110-20250116 | B34: DFK/FJP/250203/001 | C34: OPP-120324-1-FJP-DFK | D34: DFK | E34: FCJ.BX.GCS | F34: BX GCS | I34: 0 | J34: 11398 | K34: 9000000 | L34: 11398 | M34: 19948014 | N34: 9705 | O34: 485.25
A35: 【特急対応】3Dモデリング29_20250123依頼分_20250121-20250203 | B35: DFK/FJP/250203/002 | C35: OPP-120324-1-FJP-DFK | D35: DFK | E35: FCJ.BX.GCS | F35: BX GCS | I35: 0 | J35: 33984 | K35: 60 | L35: 33984 | M35: 0 | N35: 33984 | O35: 1699.2
A36: 【特急対応】3Dモデリング27_20250110依頼分_20250110-20250116 | B36: DFK/FJP/250117/001 | C36: OPP-120324-1-FJP-DFK | D36: DFK | E36: FCJ.BX.GCS | F36: BX GCS | I36: 0 | J36: 101280 | K36: 60 | L36: 101280 | M36: 0 | N36: 86230 | O36: 4311.5
A37: 3Dモデリング直線コンベア1月分 _20250110-20250124 | B37: DFK/FJP/250117/002 | C37: OPP-120324-2-FJP-DFK | D37: DFK | E37: FCJ.BX.GCS | F37: BX GCS | I37: 0 | J37: 413286 | K37: 60 | L37: 413286 | M37: 0 | N37: 382427 | O37: 19121.35
A38: AIものづくり支援環境構築1月後半分 | B38: DFK/FJP/250212/001 | C38: OPP-013124-1-FJP-DFK | D38: DFK | E38: FCJ.BX.GCS | F38: BX GCS | G38: Usui.Masahiro | I38: 0 | J38: 562500 | K38: 1150000 | L38: 562500 | M38: 21091833 | N38: 100000 | O38: 5000
A39: AAK_請求・経営管理システム連携構築業務の案件【A】、【B】、【C】フェーズ_11月 12月 | B39: AAK/FJP/250217/001 | C39: OPP-102624-1-FJP-AAK | D39: AAK | E39: FCJ.BX.GCS | F39: BX GCS | I39: 0 | J39: 16200000 | K39: #REF! | L39: 16200000 | M39: 600000 | N39: 2280000 | O39: 114000
A40: 3Dモデリング_2025年分作業 (BPO) | B40: DFK/FJP/250225/001 | C40: OPP-120324-2-FJP-DFK | D40: DFK | E40: FCJ.BX.GCS | F40: BX GCS | I40: 0 | J40: 1052773 | K40: 60 | L40: 1052773 | M40: 0 | N40: 968820 | O40: 48441
A41: 3Dモデリング特急対応_2025年分作業 (BPO) | B41: DFK/FJP/250225/003 | C41: OPP-120324-1-FJP-DFK | D41: DFK | E41: FCJ.BX.GCS | F41: BX GCS | I41: 0 | J41: 123572 | K41: #REF! | L41: 123572 | M41: 8833820 | N41: 105210 | O41: 5260.5
A42: 3Dモデリング特急対応_2025年分作業 (BPO) | B42: DFK/FJP/250225/002 | C42: OPP-120324-1-FJP-DFK | D42: DFK | E42: FCJ.BX.GCS | F42: BX GCS | I42: 0 | J42: 185652 | K42: #REF! | L42: 185652 | M42: 8339030 | N42: 158065 | O42: 7903.25
A43: AI×CADによる設計自動化に向けたロードマップ作成支援_20250217-20250331 | B43: DAIKIN/FJP/250304/001 | C43: OPP-012125-1-FJP-DAIKIN | D43: DAIKIN | E43: FJP.GMG.MCW | F43: BX GCS | G43: Usui.Masahiro | I43: 0 | J43: 2800000 | K43: 900000 | L43: 2800000 | M43: 174398574 | N43: 200000 | O43: 10000
A44: AWS 費用_202503 | B44: DAISUE/FJP/250311/001 | C44: OPP-031324-2-FJP-DAISUE | D44: DAISUE | E44: FJP.GMG.MCW | F44: BX GCS | G44: kato.fumie | I44: 0 | J44: 193625 | K44: #REF! | L44: 193625 | M44: #REF! | N44: 193625 | O44: 9681.25
A45: NXデータ移行業務のためのST9 Solid Edge ライセンスの御見積書 (1年間)_20250321-20260331 | B45: DAIKIN/FJP/250313/001 | C45: OPP-031025-1-FJP-DAIKIN | D45: DAIKIN | E45: FJP.FA.PDS | F45: BX GCS | G45: Usui.Masahiro | I45: 0 | J45: 654720 | K45: 60 | L45: 654720 | M45: 0 | N45: 654720 | O45: 32736
A46: 【特急対応】3Dモデリング32_20250226依頼分_20250228-20250303 | B46: DFK/FJP/250318/002 | C46: OPP-120324-1-FJP-DFK | D46: DFK | E46: FCJ.BX.GCS | F46: BX GCS | I46: 0 | J46: 152746 | K46: 2000000 | L46: 152746 | M46: 221142644 | N46: 139895 | O46: 6994.75
A47: 【特急対応】3Dモデリング32_#2_RMG10_20250226依頼分_2025/2/28～2025/3/3 | B47: DFK/FJP/250318/001 | C47: OPP-120324-1-FJP-DFK | D47: DFK | E47: FCJ.BX.GCS | F47: BX GCS | I47: 0 | J47: 150417 | K47: 152746 | L47: 150417 | M47: 193632539 | N47: 137761 | O47: 6888.05
A48: 【特急対応】3Dモデリング33_20250301依頼分_2025/3/3～2025/3/7 | B48: DFK/FJP/250319/007 | C48: OPP-120324-1-FJP-DFK | D48: DFK | E48: FCJ.BX.GCS | F48: BX GCS | I48: 0 | J48: 164975 | K48: 150417 | L48: 164975 | M48: 193770300 | N48: 151093 | O48: 7554.65
A49: 【特急対応】3Dモデリング33_#2_RMG10_20250301依頼分_2025/3/3～2025/3/7 | B49: DFK/FJP/250319/008 | C49: OPP-120324-1-FJP-DFK | D49: DFK | E49: FCJ.BX.GCS | F49: BX GCS | I49: 0 | J49: 21615 | K49: 164975 | L49: 21615 | M49: 221571393 | N49: 19806 | O49: 990.3
A50: 【特急対応】3Dモデリング34_20250306依頼分_2025/3/7～2025/3/14 | B50: DFK/FJP/250311/001 | C50: OPP-120324-1-FJP-DFK | D50: DFK | E50: FCJ.BX.GCS | F50: BX GCS | I50: 0 | J50: 73871 | K50: #REF! | L50: 73871 | M50: #REF! | N50: 67655 | O50: 3382.75
A51: 3Dモデリング_ZOZO ZOZOBASEつくば１ーB Pouc h架台_20250314_2025/3/14～2025/3/21 | B51: DFK/FJP/250326/001 | C51: OPP-120324-2-FJP-DFK | D51: DFK | E51: FCJ.BX.GCS | F51: BX GCS | I51: 0 | J51: 73099 | K51: 4650000 | L51: 73099 | M51: 121129032 | N51: 67005 | O51: 3350.25
A52: AIものづくり支援環境構築2月3月分＿①運用・保守支援、引継ぎ_2025/2/17～2025/4/1_FCJ.ABC | B52: DFK/FJP/250319/001 | C52: OPP-011725-1-FJP-DFK | D52: DFK | E52: FCJ.BX.GCS | F52: BX GCS | I52: 0 | J52: 1125000 | K52: 9960000 | L52: 1125000 | M52: #REF! | N52: 1125000 | O52: 56250
A53: 【特急対応】3Dモデリング35_20250324依頼分_2025/3/24～2025/4/1 | B53: DFK/FJP/250328/001 | C53: OPP-120324-1-FJP-DFK | D53: DFK | E53: FCJ.BX.GCS | F53: BX GCS | I53: 0 | J53: 86907 | K53: #REF! | L53: 86907 | M53: 15720000 | N53: 79594 | O53: 3979.7
A54: 3Dモデリング直線コンベア3月分_2025/3/24～2025/5/16 | B54: DFK/FJP/250331/002 | C54: OPP-120324-2-FJP-DFK | D54: DFK | E54: FCJ.BX.GCS | F54: BX GCS | I54: 0 | J54: 1051213 | K54: 86907 | L54: 1051213 | M54: 15799594 | N54: 962822 | O54: 48141.1
A55: 3Dモデリング_ZOZO ZOZOBASEつくば１ーB pouch架台 h架台_2025/3/25～2025/4/2 | B55: DFK/FJP/250331/003 | C55: OPP-120324-2-FJP-DFK | D55: DFK | E55: FCJ.BX.GCS | F55: BX GCS | I55: 0 | J55: 38045 | K55: #REF! | L55: 38045 | M55: 17307916 | N55: 34920 | O55: 1746
A56: 自動チェックツール開発_第3弾① ツールUI改修_2025/3/18～2025/5/6 | B56: DFK/FJP/250331/001 | C56: OPP-030725-2-FJP-DFK | D56: DFK | E56: FCJ.BX.GCS | F56: BX GCS | I56: 0 | J56: 791667 | K56: #REF! | L56: 791667 | M56: 17342836 | N56: 652423 | O56: 32621.15
A57: 自動チェックツール開発_第3弾②-1 チェック内容修正_20250318-20250506 | B57: DFK/FJP/250331/004 | C57: OPP-030725-2-FJP-DFK | D57: DFK | E57: FCJ.BX.GCS | F57: BX GCS | I57: 0 | J57: 340000 | K57: 791667 | L57: 340000 | M57: 17995259 | N57: 283000 | O57: 14150
A58: 自動チェックツール開発_第3弾②-3 チェック内容追加②_2025/3/18～2025/5/6 | B58: DFK/FJP/250331/005 | C58: OPP-030725-2-FJP-DFK | D58: DFK | E58: FCJ.BX.GCS | F58: BX GCS | I58: 0 | J58: 551250 | K58: #REF! | L58: 551250 | M58: 19403259 | N58: 456750 | O58: 22837.5
A59: 自動チェックツール開発_第3弾②-1 チェック内容追加①_20250318-20250506 | B59: DFK/FJP/250331/006 | C59: OPP-030725-2-FJP-DFK | D59: DFK | E59: FCJ.BX.GCS | F59: BX GCS | I59: 0 | J59: 859375 | K59: 551250 | L59: 859375 | M59: 19860009 | N59: 715750 | O59: 35787.5
A60: 【特急対応】3Dモデリング36_20250326依頼分_2025/3/28～2025/4/1 | B60: DFK/FJP/250402/001 | C60: OPP-120324-1-FJP-DFK | D60: DFK | E60: FCJ.BX.GCS | F60: BX GCS | I60: 0 | J60: 81485 | K60: 3224160 | L60: 81485 | M60: 168737809 | N60: 74628 | O60: 3731.4
A61: 3Dモデリング_ZOZOBASEつくば１ーB ZOZO追加分_2025/3/28～2025/4/11 | B61: DFK/FJP/250402/002 | C61: OPP-120324-2-FJP-DFK | D61: DFK | E61: FCJ.BX.GCS | F61: BX GCS | I61: 0 | J61: 82005 | K61: 81485 | L61: 82005 | M61: 168812437 | N61: 75130 | O61: 3756.5
A62: 【特急対応】3Dモデリング37_20250331依頼分_20250402-20250408 | B62: DFK/FJP/250408/001 | C62: OPP-120324-1-FJP-DFK | D62: DFK | E62: FCJ.BX.GCS | F62: BX GCS | I62: 0 | J62: 59126 | K62: #REF! | L62: 59126 | M62: 33542476 | N62: 54151 | O62: 2707.55
A63: AI活用拡大(Q2)＿AI活用に関するプロジェクトのリード_2025/4/25～2025/5/29_FAI.ABC | B63: DFK/FJP/250502/002 | C63: OPP-012725-1-FJP-DFK | D63: DFK | E63: FCJ.BX.GCS | F63: BX GCS | I63: 0 | J63: 1200000 | K63: #REF! | L63: 1200000 | M63: 8.8773843e+08 | N63: 1200000 | O63: 60000
A64: AI活用拡大(Q2)＿特殊検討技術のPoC_2025/4/25～2025/5/29_FAI.ABC | B64: DFK/FJP/250502/003 | C64: OPP-012725-1-FJP-DFK | D64: DFK | E64: FCJ.BX.GCS | F64: BX GCS | I64: 0 | J64: 980000 | K64: #REF! | L64: 980000 | M64: 1200000 | N64: 980000 | O64: 49000
A65: TCNX技術者（クォン）_20250703-20250920 | B65: DAIKIN/FJP/250422/005 | C65: OPP-102924-6-FJP-DAIKIN | D65: DAIKIN | E65: FJP.FA.PDS | F65: BX GCS | G65: Usui.Masahiro | I65: 0 | J65: 2067200 | K65: 10500000 | L65: 2067200 | M65: 1.8958313e+08 | N65: 2067200 | O65: 103360
A66: TCNX技術者（フィ）_20250703-20250920 | B66: DAIKIN/FJP/250418/001 | C66: OPP-102924-6-FJP-DAIKIN | D66: DAIKIN | E66: FJP.FA.PDS | F66: BX GCS | G66: Usui.Masahiro | I66: 0 | J66: 2176000 | K66: #REF! | L66: 2176000 | M66: 1.9165033e+08 | N66: 2176000 | O66: 108800
A67: NX, TC業務支援_20250515-20250613 | B67: DAIKIN/FJP/250428/001 | C67: OPP-102924-6-FJP-DAIKIN | D67: DAIKIN | E67: FJP.FA.PDS | F67: BX GCS | G67: Usui.Masahiro | I67: 0 | J67: 450000 | K67: #REF! | L67: 450000 | M67: 24008200 | N67: 450000 | O67: 22500
A68: 基幹システムリプレイスに伴う業務要件定義_202506-202509 | B68: DAISUE/FJP/250428/001 | C68: OPP-122324-1-FJP-DAISUE | D68: DAISUE | E68: FJP.GMG.MCW | F68: BX GCS | G68: Kato.Fumie | I68: 0 | J68: 58100000 | K68: #REF! | L68: 58100000 | M68: 24458200 | N68: 10600000 | O68: 530000
A69: NX, TC業務支援_20250617-20250630 | B69: DAIKIN/FJP/250430/001 | C69: OPP-102924-6-FJP-DAIKIN | D69: DAIKIN | E69: FJP.FA.PDS | F69: BX GCS | G69: Usui.Masahiro | I69: 0 | J69: 400000 | K69: #REF! | L69: 400000 | M69: 35058200 | N69: 400000 | O69: 20000
A70: AAK_業務改善・デジタル化の案件【C】フェーズ_2025年4月 | B70: AAK/FJP/250425/002 | C70: OPP-040825-1-FJP-AAK | D70: AAK | E70: FCJ.BX.GCS | F70: BX GCS | I70: 0 | J70: 600000 | K70: 60 | L70: 600000 | M70: 0 | N70: 480000 | O70: 24000
A71: 【特急対応】3Dモデリング38_20250409依頼分_2025/4/9～2025/4/15 | B71: DFK/FJP/250430/001 | C71: OPP-120324-1-FJP-DFK | D71: DFK | E71: FCJ.BX.GCS | F71: BX GCS | I71: 0 | J71: 52515 | K71: 1500000 | L71: 52515 | M71: 239059582 | N71: 48096 | O71: 2404.8
A72: 【特急対応】3Dモデリング39_20250416依頼分_2025/4/17～2025/5/6 | B72: DFK/FJP/250424/002 | C72: OPP-120324-1-FJP-DFK | D72: DFK | E72: FCJ.BX.GCS | F72: BX GCS | I72: 0 | J72: 76954 | K72: 60 | L72: 76954 | M72: 0 | N72: 70479 | O72: 3523.95
A73: セッケイアウトプットノカイカク 3Dモデリング・検図_2025/4/17～2025/6/6 | B73: DFK/FJP/250424/001 | C73: OPP-120324-2-FJP-DFK | D73: DFK | E73: FCJ.BX.GCS | F73: BX GCS | I73: 0 | J73: 818521 | K73: #REF! | L73: 818521 | M73: #REF! | N73: 749693 | O73: 37484.65
A74: セッケイアウトプットノカイカク Revup 対応_2025/4/21～2025/5/9 | B74: DFK/FJP/250501/001 | C74: OPP-120324-2-FJP-DFK | D74: DFK | E74: FCJ.BX.GCS | F74: BX GCS | I74: 0 | J74: 188733 | K74: #REF! | L74: 188733 | M74: 27448268 | N74: 172920 | O74: 8646
A75: 【特急対応】3Dモデリング40_20250422依頼分_2025/4/22～2025/5/12 | B75: DFK/FJP/250425/001 | C75: OPP-120324-1-FJP-DFK | D75: DFK | E75: FCJ.BX.GCS | F75: BX GCS | I75: 0 | J75: 89990 | K75: #REF! | L75: 89990 | M75: 9621188 | N75: 82419 | O75: 4120.95
A76: AI活用拡大(Q2)＿運用引継ぎ、及び関連支援_20250428-20250531_FAI.ABC | B76: DFK/FJP/250515/003 | C76: OPP-012725-1-FJP-DFK | D76: DFK | E76: FCJ.BX.GCS | F76: BX GCS | I76: 0 | J76: 2386250 | K76: 1373750 | L76: 2386250 | M76: #REF! | N76: 2386250 | O76: 119312.5
A77: RMG10モデリング_20250506-20250509 | B77: DFK/FJP/250515/001 | C77: OPP-120324-2-FJP-DFK | D77: DFK | E77: FCJ.BX.GCS | F77: BX GCS | I77: 0 | J77: 29897 | K77: #REF! | L77: 29897 | M77: 12176703 | N77: 29897 | O77: 1494.85
A78: 【特急対応】3Dモデリング41_20250512依頼分_20250513-20250521 | B78: DFK/FJP/250522/002 | C78: OPP-120324-1-FJP-DFK | D78: DFK | E78: FCJ.BX.GCS | F78: BX GCS | I78: 0 | J78: 125941 | K78: #REF! | L78: 125941 | M78: 33148347 | N78: 125941 | O78: 6297.05
A79: 設計アウトプットの改革 IDW作成_20250514-20250606 | B79: DFK/FJP/250522/001 | C79: OPP-120324-2-FJP-DFK | D79: DFK | E79: FCJ.BX.GCS | F79: BX GCS | I79: 0 | J79: 64622 | K79: 60 | L79: 64622 | M79: 0 | N79: 64622 | O79: 3231.1
A80: 【特急対応】3Dモデリング42_20250520依頼分_20250520-20250602 | B80: DFK/FJP/250528/001 | C80: OPP-120324-1-FJP-DFK | D80: DFK | E80: FCJ.BX.GCS | F80: BX GCS | I80: 0 | J80: 136437 | K80: #REF! | L80: 136437 | M80: 41731443 | N80: 136437 | O80: 6821.85
A81: 設計アウトプットの改革 モデリング・検図_20250522-20250630 | B81: DFK/FJP/250528/002 | C81: OPP-120324-2-FJP-DFK | D81: DFK | E81: FCJ.BX.GCS | F81: BX GCS | I81: 0 | J81: 926673 | K81: 136437 | L81: 926673 | M81: 41867880 | N81: 926673 | O81: 46333.65
A82: FDNイベント_ベトナム出張_20250801-20250829 | B82: DAISUE/FJP/250617/001 | C82: OPP-122324-1-FJP-DAISUE | D82: DAISUE | E82: FJP.GMG.MCW | F82: BX GCS | G82: Kato.Fumie | I82: 0 | J82: 678700 | K82: 1550000 | L82: 678700 | M82: #REF! | N82: 678700 | O82: 33935
A83: NX,TC業務支援Q2_20250704-20250930 | B83: DAIKIN/FJP/250705/002 | C83: OPP-102924-6-FJP-DAIKIN | D83: DAIKIN | E83: FJP.FA.PDS | F83: BX GCS | G83: Usui.Masahiro | I83: 0 | J83: 2400000 | K83: 2000000 | L83: 2400000 | M83: 262502686 | N83: 2400000 | O83: 120000
A84: 【特急対応】3Dモデリング43_20250529依頼分_20250529-20250605 | B84: DFK/FJP/250617/001 | C84: OPP-120324-1-FJP-DFK | D84: DFK | E84: FCJ.BX.GCS | F84: BX GCS | I84: 0 | J84: 95581 | K84: 60 | L84: 95581 | M84: 0 | N84: 95581 | O84: 4779.05
A85: AI活用拡大(Q2)＿設計支援AI開発 AI物作り支援6月_20250528-20250701_FAI.ABC | B85: DFK/FJP/250614/001 | C85: OPP-012725-1-FJP-DFK | D85: DFK | E85: FCJ.BX.GCS | F85: BX GCS | I85: 0 | J85: 4510000 | K85: #REF! | L85: 4510000 | M85: 203396831 | N85: 4510000 | O85: 225500
A86: 【特急対応】3Dモデリング44_20250605依頼分_2025/6/6～2025/6/11 | B86: DFK/FJP/250613/001 | C86: OPP-120324-1-FJP-DFK | D86: DFK | E86: FCJ.BX.GCS | F86: BX GCS | I86: 0 | J86: 82164 | K86: #REF! | L86: 82164 | M86: 20206460 | N86: 82164 | O86: 4108.2
A87: 設計アウトプットの改革 IDW作成_20240606発注分_2025/6/6～2025/7/2 | B87: DFK/FJP/250703/001 | C87: OPP-120324-2-FJP-DFK | D87: DFK | E87: FCJ.BX.GCS | F87: BX GCS | I87: 0 | J87: 266897 | K87: #REF! | L87: 266897 | M87: 1207164 | N87: 266897 | O87: 13344.85
A88: 【特急対応】3Dモデリング45_20250616依頼分_20250616-20250618 | B88: DFK/FJP/250703/004 | C88: OPP-120324-1-FJP-DFK | D88: DFK | E88: FCJ.BX.GCS | F88: BX GCS | I88: 0 | J88: 96524 | K88: 60 | L88: 96524 | M88: 0 | N88: 96524 | O88: 4826.2
A89: 【特急対応】3Dモデリング46_20250623依頼分_2025/6/23～2025/7/1 | B89: DFK/FJP/250703/003 | C89: OPP-120324-1-FJP-DFK | D89: DFK | E89: FCJ.BX.GCS | F89: BX GCS | I89: 0 | J89: 161539 | K89: #REF! | L89: 161539 | M89: #REF! | N89: 161539 | O89: 8076.95
A90: AI活用拡大(Q3)＿度AIものづくり支援7-9月活動_2025/6/27～2025/10/1_FAI.ABC | B90: DFK/FJP/250705/001 | C90: OPP-030725-1-FJP-DFK | D90: DFK | E90: FCJ.BX.GCS | F90: BX GCS | I90: 0 | J90: 10845000 | K90: #REF! | L90: 10845000 | M90: 9103463 | N90: 10845000 | O90: 542250
A91: FDNイベント_ベトナム出張_ホテル費用_20250801-20250829 | B91: DAISUE/FJP/250708/001 | C91: OPP-122324-1-FJP-DAISUE | D91: DAISUE | E91: FJP.GMG.MCW | F91: BX GCS | G91: Kato.Fumie | I91: 0 | J91: 200000 | K91: 2750000 | L91: 200000 | M91: 201509821 | N91: 200000 | O91: 10000
A92: 設計アウトプットの改革 3Dモデリング_20240626発注分_20250626-20250711 | B92: DFK/FJP/250717/001 | C92: OPP-120324-2-FJP-DFK | D92: DFK | E92: FCJ.BX.GCS | F92: BX GCS | I92: 0 | J92: 137391 | K92: 60 | L92: 137391 | M92: 0 | N92: 137391 | O92: 6869.55
A93: 【特急対応】3Dモデリング47_20250703依頼分_2025/7/3～2025/7/9 | B93: DFK/FJP/250717/002 | C93: OPP-120324-1-FJP-DFK | D93: DFK | E93: FCJ.BX.GCS | F93: BX GCS | I93: 0 | J93: 127354 | K93: #REF! | L93: 127354 | M93: #REF! | N93: 127354 | O93: 6367.7
A94: 【特急対応】3Dモデリング48_20250710依頼分_2025/7/10～2025/7/17 | B94: DFK/FJP/250729/002 | C94: OPP-120324-1-FJP-DFK | D94: DFK | E94: FCJ.BX.GCS | F94: BX GCS | I94: 0 | J94: 135533 | K94: #REF! | L94: 135533 | M94: 9950000 | N94: 135533 | O94: 6776.65
A95: ﾊﾟﾚｯﾄｺﾝﾍﾞﾔｾｲｻﾝｾｲｶｲﾊﾂ モデル作成_20240717発注分_2025/7/17～2025/7/25 | B95: DFK/FJP/250730/001 | C95: OPP-120324-2-FJP-DFK | D95: DFK | E95: FCJ.BX.GCS | F95: BX GCS | I95: 0 | J95: 113475 | K95: 1214000 | L95: 113475 | M95: #REF! | N95: 113475 | O95: 5673.75
A96: 【特急対応】3Dモデリング49_20250718依頼分_2025/7/18～2025/7/24 | B96: DFK/FJP/250729/001 | C96: OPP-120324-1-FJP-DFK | D96: DFK | E96: FCJ.BX.GCS | F96: BX GCS | I96: 0 | J96: 213476 | K96: 60 | L96: 213476 | M96: 0 | N96: 213476 | O96: 10673.8
A97: 設計アウトプットの改革 IDW作成_20240703発注分_2025/7/3～2025/8/8 | B97: DFK/FJP/250822/003 | C97: OPP-120324-2-FJP-DFK | D97: DFK | E97: FCJ.BX.GCS | F97: BX GCS | I97: 0 | J97: 716866 | K97: #REF! | L97: 716866 | M97: #REF! | N97: 716866 | O97: 35843.3
A98: 【特急対応】3Dモデリング50_20250730依頼分_2025/7/30～2025/8/1 | B98: DFK/FJP/250822/001 | C98: OPP-120324-1-FJP-DFK | D98: DFK | E98: FCJ.BX.GCS | F98: BX GCS | I98: 0 | J98: 216943 | K98: 4200000 | L98: 216943 | M98: 100770296 | N98: 216943 | O98: 10847.15
A99: ﾊﾟﾚｯﾄｺﾝﾍﾞﾔｾｲｻﾝｾｲｶｲﾊﾂ モデル作成_20240725発注分_2025/7/25～2025/7/28 | B99: DFK/FJP/250808/001 | C99: OPP-120324-2-FJP-DFK | D99: DFK | E99: FCJ.BX.GCS | F99: BX GCS | I99: 0 | J99: 129375 | K99: #REF! | L99: 129375 | M99: #REF! | N99: 129375 | O99: 6468.75
A100: 【特急対応】3Dモデリング51_20250808依頼分_2025/8/8～2025/8/12 | B100: DFK/FJP/250822/002 | C100: OPP-120324-1-FJP-DFK | D100: DFK | E100: FCJ.BX.GCS | F100: BX GCS | I100: 0 | J100: 160597 | K100: #REF! | L100: 160597 | M100: 346318 | N100: 160597 | O100: 8029.85
...

Sheet Sheet1
B1: チーム | C1: 顧客 | E1: 案件名 | F1: 種類 | G1: 状況 | H1: アサイン | I1: 確度 | J1: 7月 | K1: 8月 | L1: 9月 | M1: 10月 | N1: 11月 | O1: 12月 | P1: 計
A2: 1 | B2: 製造T | C2: LIXIL | E2: BPO業務自動化支援 | F2: 新規 | G2: 提案中。7月中にベンダーー選定 受注内示、3か月 | H2: 鷹野、松田 | I2: B | J2: 0 | K2: 4800000 | L2: 7100000 | M2: 7100000 | N2: 7100000 | O2: 7100000 | P2: =SUM(J2:O2) -> 33200000
A3: 2 | B3: 製造T | C3: Daifuku Co., Ltd. | E3: AIものづくり支援環境構築 | F3: 継続 | G3: 継続 | H3: 境、方 | I3: A | J3: 3200000 | K3: 2050000 | L3: 2050000 | M3: 2050000 | N3: 2050000 | O3: 2050000 | P3: =SUM(J3:O3) -> 13450000
A4: 3 | B4: 製造T | C4: オリックス銀行株式会社 | E4: RPA運用支援＆akaBot検証 | F4: 新規 | G4: 7/9キックオフ。7/15案件開始 | H4: バンクス | I4: A | J4: 2000000 | K4: 2000000 | L4: 2000000 | M4: 2000000 | N4: 2000000 | O4: 2000000 | P4: =SUM(J4:O4) -> 12000000
A5: 4 | B5: 製造T | C5: ダイキン | E5: グローバルデータ基盤構築 | F5: 継続 | G5: 7/11概算見積予定 | H5: 臼井、境 | I5: B | J5: 1950000 | K5: 1950000 | L5: 1950000 | M5: 1950000 | N5: 1950000 | O5: 1950000 | P5: =SUM(J5:O5) -> 11700000
A6: 5 | B6: 製造T | C6: DNP | E6: DNPのBPO業務 | F6: 新規 | G6: 提案中 確度高そう。。。 業務整理＋自動化、システム化 | H6: 鷹野、川口、BP | I6: D | J6: 0 | K6: 2250000 | L6: 2250000 | M6: 2250000 | N6: 2250000 | O6: 2250000 | P6: =SUM(J6:O6) -> 11250000
A7: 6 | B7: 製造T | C7: Mitsubishi UFJ Trust System | E7: UiPath開発 | F7: 新規 | G7: 7/7見積提示済 | H7: 鷹野、松田 | I7: C | J7: 0 | K7: 0 | L7: 0 | M7: 3125000 | N7: 3125000 | O7: 3125000 | P7: =SUM(J7:O7) -> 9375000
A8: 7 | B8: 製造T | C8: ITEC阪急阪神 | E8: i-PLAT調査、導入支援 | F8: 新規 | G8: パッケージ製品評価の提案書作成中 | H8: 鷹野、松田 | I8: D | J8: 0 | K8: 1000000 | L8: 1000000 | M8: 1000000 | N8: 1000000 | O8: 1000000 | P8: =SUM(J8:O8) -> 5000000
A9: 8 | B9: 製造T | C9: IODATA | E9: PM/PL要員育成ロードマップ作成、教育支援 | F9: 新規 | G9: 予算確保済。10月開始予定 | H9: 臼井 | I9: B | J9: 0 | K9: 0 | L9: 0 | M9: 1350000 | N9: 1350000 | O9: 1350000 | P9: =SUM(J9:O9) -> 4050000
A10: 9 | B10: 製造T | C10: Daiwa House | E10: 大和ハウス AI支援 | F10: 新規 | G10: NDA締結し、PoC提案中 | H10: 川口 | I10: C | K10: 500000 | L10: 1000000 | M10: 1000000 | N10: 1000000 | O10: 500000 | P10: =SUM(J10:O10) -> 4000000
A11: 10 | B11: 製造T | C11: YKK AP Inc. | E11: YKKAP_次期AP-CADシステム刷新_開発フェーズ | F11: 継続 | G11: 7月受注予定 | H11: 鷹野、松田 | I11: B | J11: 875000 | K11: 1750000 | L11: 875000 | M11: 0 | N11: 0 | O11: 0 | P11: =SUM(J11:O11) -> 3500000
A12: 11 | B12: 製造T | C12: SCSK | E12: BPR案件、DXチームからの引継ぎ。 | F12: 継続 | G12: 7/10訪問、提案 | H12: 臼井、松田 | I12: D | J12: 0 | K12: 1100000 | L12: 1100000 | M12: 1100000 | P12: =SUM(J12:O12) -> 3300000
A13: 12 | B13: 製造T | C13: ダイキン | E13: PLMコンサル | F13: 継続 | G13: 7/10見積提示、7月受注予定 | H13: 川口 | I13: B | J13: 925000 | K13: 925000 | L13: 925000 | P13: =SUM(J13:O13) -> 2775000
A14: 13 | B14: 製造T | C14: 野村不動産 | E14: 営業支援ツール | F14: 新規 | G14: 7月開始 | H14: 方 | I14: A | K14: 2764000 | M14: 0 | N14: 0 | O14: 0 | P14: =SUM(J14:O14) -> 2764000
A15: 14 | B15: 製造T | C15: Daifuku Co., Ltd. | E15: 3D CADチェックツール開発(第二弾) | F15: 継続 | G15: 7月受注予定 | H15: 川口 | I15: A | J15: 250000 | K15: 250000 | L15: 0 | M15: 0 | N15: 0 | O15: 0 | P15: =SUM(J15:O15) -> 500000
